Workbook

Sheet Test Summary
A1: FIWDEE – Unit Test Design
A2: No | B2: Project | C2: Test Strategy | D2: No. of Test Cases | E2: Pass | F2: Fail | G2: No run | H2: Block | I2: Remark / Defect ID
A3: Booking
A4: 1 | B4: UT01 – BookingServiceImpl.createBooking – ข้อมูลนำเข้าและผู้ทำรายการ | C4: Weak Robust Equivalence Class Testing | D4: =COUNTA(UT01_CreateBooking_EC!$A$28:$A$42) -> 15 | E4: =COUNTIF(UT01_CreateBooking_EC!$J$28:$J$42,"Pass") -> 15 | F4: =COUNTIF(UT01_CreateBooking_EC!$J$28:$J$42,"Fail") -> 0 | G4: =COUNTIF(UT01_CreateBooking_EC!$J$28:$J$42,"No run") -> 0 | H4: =COUNTIF(UT01_CreateBooking_EC!$J$28:$J$42,"Block") -> 0
A5: 2 | B5: UT02 – BookingServiceImpl.createBooking – จัดสรรหมอนวดและห้อง | C5: Decision Table (Limited Entry) | D5: =COUNTA(UT02_CreateBooking_DT!$B$29:$B$38) -> 10 | E5: =COUNTIF(UT02_CreateBooking_DT!$H$29:$H$38,"Pass") -> 10 | F5: =COUNTIF(UT02_CreateBooking_DT!$H$29:$H$38,"Fail") -> 0 | G5: =COUNTIF(UT02_CreateBooking_DT!$H$29:$H$38,"No run") -> 0 | H5: =COUNTIF(UT02_CreateBooking_DT!$H$29:$H$38,"Block") -> 0
A6: 3 | B6: UT03 – BookingServiceImpl.createBooking – ช่วงเวลาที่จองได้ | C6: Robustness Testing | D6: =COUNTA(UT03_CreateBooking_Time_BVA!$A$11:$A$23) -> 13 | E6: =COUNTIF(UT03_CreateBooking_Time_BVA!$G$11:$G$23,"Pass") -> 13 | F6: =COUNTIF(UT03_CreateBooking_Time_BVA!$G$11:$G$23,"Fail") -> 0 | G6: =COUNTIF(UT03_CreateBooking_Time_BVA!$G$11:$G$23,"No run") -> 0 | H6: =COUNTIF(UT03_CreateBooking_Time_BVA!$G$11:$G$23,"Block") -> 0
A7: 4 | B7: UT04 – BookingRepository.findConflictingRoomBookingsWithCleaningBuffer + createBooking – เวลาทับซ้อน | C7: Robustness Testing (ขอบด้านเดียว) | D7: =COUNTA(UT04_Overlap_Buffer_BVA!$A$11:$A$23) -> 13 | E7: =COUNTIF(UT04_Overlap_Buffer_BVA!$H$11:$H$23,"Pass") -> 13 | F7: =COUNTIF(UT04_Overlap_Buffer_BVA!$H$11:$H$23,"Fail") -> 0 | G7: =COUNTIF(UT04_Overlap_Buffer_BVA!$H$11:$H$23,"No run") -> 0 | H7: =COUNTIF(UT04_Overlap_Buffer_BVA!$H$11:$H$23,"Block") -> 0
A8: 5 | B8: UT05 – BookingServiceImpl.cancelBooking – ยกเลิกการจอง | C8: Decision Table (Extended Entry) | D8: =COUNTA(UT05_CancelBooking_DT!$B$34:$B$45) -> 12 | E8: =COUNTIF(UT05_CancelBooking_DT!$I$34:$I$45,"Pass") -> 12 | F8: =COUNTIF(UT05_CancelBooking_DT!$I$34:$I$45,"Fail") -> 0 | G8: =COUNTIF(UT05_CancelBooking_DT!$I$34:$I$45,"No run") -> 0 | H8: =COUNTIF(UT05_CancelBooking_DT!$I$34:$I$45,"Block") -> 0
A9: 6 | B9: UT06 – BookingServiceImpl.cancelBooking – กฎลูกค้ายกเลิกล่วงหน้า ≥ 2 ชั่วโมง | C9: Robustness Testing (ขอบด้านเดียว) | D9: =COUNTA(UT06_Cancel_2h_BVA!$A$11:$A$15) -> 5 | E9: =COUNTIF(UT06_Cancel_2h_BVA!$F$11:$F$15,"Pass") -> 5 | F9: =COUNTIF(UT06_Cancel_2h_BVA!$F$11:$F$15,"Fail") -> 0 | G9: =COUNTIF(UT06_Cancel_2h_BVA!$F$11:$F$15,"No run") -> 0 | H9: =COUNTIF(UT06_Cancel_2h_BVA!$F$11:$F$15,"Block") -> 0
A10: 7 | B10: UT07 – BookingServiceImpl.getBookingById – สิทธิ์การดูรายการจอง | C10: Decision Table (Limited Entry) | D10: =COUNTA(UT07_GetBookingById_DT!$B$26:$B$33) -> 7 | E10: =COUNTIF(UT07_GetBookingById_DT!$G$26:$G$33,"Pass") -> 7 | F10: =COUNTIF(UT07_GetBookingById_DT!$G$26:$G$33,"Fail") -> 0 | G10: =COUNTIF(UT07_GetBookingById_DT!$G$26:$G$33,"No run") -> 0 | H10: =COUNTIF(UT07_GetBookingById_DT!$G$26:$G$33,"Block") -> 0
A11: 8 | B11: UT08 – Booking State Pattern (Booking.confirm/checkIn/startService/complete/cancel/markNoShow) | C11: Decision Table (Extended Entry) แบบ State Transition Table | D11: =COUNTA(UT08_BookingState_DT!$B$31:$B$75) -> 44 | E11: =COUNTIF(UT08_BookingState_DT!$H$31:$H$75,"Pass") -> 44 | F11: =COUNTIF(UT08_BookingState_DT!$H$31:$H$75,"Fail") -> 0 | G11: =COUNTIF(UT08_BookingState_DT!$H$31:$H$75,"No run") -> 0 | H11: =COUNTIF(UT08_BookingState_DT!$H$31:$H$75,"Block") -> 0
A12: 9 | B12: UT09 – BookingStateFactory.getState(BookingStatus) | C12: Strong Normal Equivalence Class Testing (ทุกค่าใน enum) | D12: =COUNTA(UT09_StateFactory_EC!$A$24:$A$31) -> 7 | E12: =COUNTIF(UT09_StateFactory_EC!$E$24:$E$31,"Pass") -> 7 | F12: =COUNTIF(UT09_StateFactory_EC!$E$24:$E$31,"Fail") -> 0 | G12: =COUNTIF(UT09_StateFactory_EC!$E$24:$E$31,"No run") -> 0 | H12: =COUNTIF(UT09_StateFactory_EC!$E$24:$E$31,"Block") -> 0
A13: 10 | B13: UT10 – AvailabilityServiceImpl.checkAvailability – จำนวนรอบเวลาตามระยะเวลาบริการ | C13: Robustness Testing | D13: =COUNTA(UT10_Availability_BVA!$A$12:$A$19) -> 8 | E13: =COUNTIF(UT10_Availability_BVA!$E$12:$E$19,"Pass") -> 8 | F13: =COUNTIF(UT10_Availability_BVA!$E$12:$E$19,"Fail") -> 0 | G13: =COUNTIF(UT10_Availability_BVA!$E$12:$E$19,"No run") -> 0 | H13: =COUNTIF(UT10_Availability_BVA!$E$12:$E$19,"Block") -> 0
A14: 11 | B14: UT11 – AvailabilityServiceImpl.checkAvailability – สภาพร้านและทรัพยากร | C14: Weak Robust Equivalence Class Testing | D14: =COUNTA(UT11_Availability_EC!$A$24:$A$32) -> 8 | E14: =COUNTIF(UT11_Availability_EC!$G$24:$G$32,"Pass") -> 8 | F14: =COUNTIF(UT11_Availability_EC!$G$24:$G$32,"Fail") -> 0 | G14: =COUNTIF(UT11_Availability_EC!$G$24:$G$32,"No run") -> 0 | H14: =COUNTIF(UT11_Availability_EC!$G$24:$G$32,"Block") -> 0
A15: 12 | B15: UT12 – BookingMapper (toMyBookingResponse / toBookingResponse / list) | C15: Weak Normal Equivalence Class Testing | D15: =COUNTA(UT12_BookingMapper_EC!$A$23:$A$30) -> 7 | E15: =COUNTIF(UT12_BookingMapper_EC!$F$23:$F$30,"Pass") -> 7 | F15: =COUNTIF(UT12_BookingMapper_EC!$F$23:$F$30,"Fail") -> 0 | G15: =COUNTIF(UT12_BookingMapper_EC!$F$23:$F$30,"No run") -> 0 | H15: =COUNTIF(UT12_BookingMapper_EC!$F$23:$F$30,"Block") -> 0
A16: Payment
A17: 13 | B17: UT13 – PaymentServiceImpl.processPayment – ตรวจเงื่อนไขและผลการชำระ | C17: Decision Table (Limited Entry) | D17: =COUNTA(UT13_ProcessPayment_DT!$B$30:$B$37) -> 7 | E17: =COUNTIF(UT13_ProcessPayment_DT!$H$30:$H$37,"Pass") -> 7 | F17: =COUNTIF(UT13_ProcessPayment_DT!$H$30:$H$37,"Fail") -> 0 | G17: =COUNTIF(UT13_ProcessPayment_DT!$H$30:$H$37,"No run") -> 0 | H17: =COUNTIF(UT13_ProcessPayment_DT!$H$30:$H$37,"Block") -> 0
A18: 14 | B18: UT14 – PaymentServiceImpl.processPayment – ส่วนลดและสถานะ booking หลังชำระ | C18: Weak Robust Equivalence Class Testing | D18: =COUNTA(UT14_Payment_Promo_Status_EC!$A$23:$A$33) -> 10 | E18: =COUNTIF(UT14_Payment_Promo_Status_EC!$G$23:$G$33,"Pass") -> 7 | F18: =COUNTIF(UT14_Payment_Promo_Status_EC!$G$23:$G$33,"Fail") -> 3 | G18: =COUNTIF(UT14_Payment_Promo_Status_EC!$G$23:$G$33,"No run") -> 0 | H18: =COUNTIF(UT14_Payment_Promo_Status_EC!$G$23:$G$33,"Block") -> 0 | I18: DEF-008, DEF-009, DEF-010
A19: 15 | B19: UT15 – FixedAmountDiscountStrategy (WELCOME100) | C19: Robustness Testing | D19: =COUNTA(UT15_FixedDiscount_BVA!$A$12:$A$25) -> 13 | E19: =COUNTIF(UT15_FixedDiscount_BVA!$F$12:$F$25,"Pass") -> 13 | F19: =COUNTIF(UT15_FixedDiscount_BVA!$F$12:$F$25,"Fail") -> 0 | G19: =COUNTIF(UT15_FixedDiscount_BVA!$F$12:$F$25,"No run") -> 0 | H19: =COUNTIF(UT15_FixedDiscount_BVA!$F$12:$F$25,"Block") -> 0
A20: 16 | B20: UT16 – PercentageDiscountStrategy (FIWDEE20) | C20: Weak Robust Equivalence Class Testing | D20: =COUNTA(UT16_PercentDiscount_EC!$A$20:$A$28) -> 8 | E20: =COUNTIF(UT16_PercentDiscount_EC!$F$20:$F$28,"Pass") -> 8 | F20: =COUNTIF(UT16_PercentDiscount_EC!$F$20:$F$28,"Fail") -> 0 | G20: =COUNTIF(UT16_PercentDiscount_EC!$F$20:$F$28,"No run") -> 0 | H20: =COUNTIF(UT16_PercentDiscount_EC!$F$20:$F$28,"Block") -> 0
A21: 17 | B21: UT17 – DiscountStrategyFactory.findStrategy(promoCode) | C21: Weak Robust Equivalence Class Testing | D21: =COUNTA(UT17_DiscountFactory_EC!$A$20:$A$27) -> 7 | E21: =COUNTIF(UT17_DiscountFactory_EC!$F$20:$F$27,"Pass") -> 7 | F21: =COUNTIF(UT17_DiscountFactory_EC!$F$20:$F$27,"Fail") -> 0 | G21: =COUNTIF(UT17_DiscountFactory_EC!$F$20:$F$27,"No run") -> 0 | H21: =COUNTIF(UT17_DiscountFactory_EC!$F$20:$F$27,"Block") -> 0
A22: 18 | B22: UT18 – PaymentStrategyFactory + Cash/QR/CardPaymentStrategy | C22: Strong Normal Equivalence Class Testing (ทุกค่าใน PaymentMethod) | D22: =COUNTA(UT18_PaymentStrategy_EC!$A$21:$A$30) -> 9 | E22: =COUNTIF(UT18_PaymentStrategy_EC!$F$21:$F$30,"Pass") -> 9 | F22: =COUNTIF(UT18_PaymentStrategy_EC!$F$21:$F$30,"Fail") -> 0 | G22: =COUNTIF(UT18_PaymentStrategy_EC!$F$21:$F$30,"No run") -> 0 | H22: =COUNTIF(UT18_PaymentStrategy_EC!$F$21:$F$30,"Block") -> 0
A23: Refund
A24: 19 | B24: UT19 – RefundServiceImpl.processRefund – จำนวนเงินคืน | C24: Robustness Testing | D24: =COUNTA(UT19_Refund_Amount_BVA!$A$12:$A$18) -> 6 | E24: =COUNTIF(UT19_Refund_Amount_BVA!$E$12:$E$18,"Pass") -> 6 | F24: =COUNTIF(UT19_Refund_Amount_BVA!$E$12:$E$18,"Fail") -> 0 | G24: =COUNTIF(UT19_Refund_Amount_BVA!$E$12:$E$18,"No run") -> 0 | H24: =COUNTIF(UT19_Refund_Amount_BVA!$E$12:$E$18,"Block") -> 0
A25: 20 | B25: UT20 – RefundServiceImpl – เงื่อนไขอื่นของการคืนเงิน | C25: Weak Robust Equivalence Class Testing | D25: =COUNTA(UT20_Refund_EC!$A$22:$A$31) -> 9 | E25: =COUNTIF(UT20_Refund_EC!$F$22:$F$31,"Pass") -> 9 | F25: =COUNTIF(UT20_Refund_EC!$F$22:$F$31,"Fail") -> 0 | G25: =COUNTIF(UT20_Refund_EC!$F$22:$F$31,"No run") -> 0 | H25: =COUNTIF(UT20_Refund_EC!$F$22:$F$31,"Block") -> 0
A26: Queue
A27: 21 | B27: UT21 – QueueServiceImpl.checkInBooking – ช่วงเวลาที่ check-in ได้ | C27: Robustness Testing (ขอบด้านเดียว) | D27: =COUNTA(UT21_CheckIn_Window_BVA!$A$12:$A$17) -> 5 | E27: =COUNTIF(UT21_CheckIn_Window_BVA!$F$12:$F$17,"Pass") -> 5 | F27: =COUNTIF(UT21_CheckIn_Window_BVA!$F$12:$F$17,"Fail") -> 0 | G27: =COUNTIF(UT21_CheckIn_Window_BVA!$F$12:$F$17,"No run") -> 0 | H27: =COUNTIF(UT21_CheckIn_Window_BVA!$F$12:$F$17,"Block") -> 0
A28: 22 | B28: UT22 – QueueServiceImpl – สถานะ booking ตอน check-in และเลขคิว | C28: Weak Robust Equivalence Class Testing | D28: =COUNTA(UT22_CheckIn_Queue_EC!$A$22:$A$31) -> 9 | E28: =COUNTIF(UT22_CheckIn_Queue_EC!$F$22:$F$31,"Pass") -> 9 | F28: =COUNTIF(UT22_CheckIn_Queue_EC!$F$22:$F$31,"Fail") -> 0 | G28: =COUNTIF(UT22_CheckIn_Queue_EC!$F$22:$F$31,"No run") -> 0 | H28: =COUNTIF(UT22_CheckIn_Queue_EC!$F$22:$F$31,"Block") -> 0
A29: 23 | B29: UT23 – QueueServiceImpl.updateQueueStatus – การเปลี่ยนสถานะคิว | C29: Decision Table (Extended Entry) แบบ State Transition Table | D29: =COUNTA(UT23_QueueStatus_DT!$B$29:$B$54) -> 25 | E29: =COUNTIF(UT23_QueueStatus_DT!$G$29:$G$54,"Pass") -> 25 | F29: =COUNTIF(UT23_QueueStatus_DT!$G$29:$G$54,"Fail") -> 0 | G29: =COUNTIF(UT23_QueueStatus_DT!$G$29:$G$54,"No run") -> 0 | H29: =COUNTIF(UT23_QueueStatus_DT!$G$29:$G$54,"Block") -> 0
A30: 24 | B30: UT24 – TherapistExecutionServiceImpl – เริ่ม/จบการให้บริการ | C30: Decision Table (Extended Entry) | D30: =COUNTA(UT24_TherapistExec_DT!$B$28:$B$35) -> 7 | E30: =COUNTIF(UT24_TherapistExec_DT!$H$28:$H$35,"Pass") -> 7 | F30: =COUNTIF(UT24_TherapistExec_DT!$H$28:$H$35,"Fail") -> 0 | G30: =COUNTIF(UT24_TherapistExec_DT!$H$28:$H$35,"No run") -> 0 | H30: =COUNTIF(UT24_TherapistExec_DT!$H$28:$H$35,"Block") -> 0
A31: Review
A32: 25 | B32: UT25 – ReviewServiceImpl.submitReview – คะแนน 3 ด้าน | C32: Robustness Testing | D32: =COUNTA(UT25_Review_Rating_BVA!$A$12:$A$30) -> 18 | E32: =COUNTIF(UT25_Review_Rating_BVA!$G$12:$G$30,"Pass") -> 18 | F32: =COUNTIF(UT25_Review_Rating_BVA!$G$12:$G$30,"Fail") -> 0 | G32: =COUNTIF(UT25_Review_Rating_BVA!$G$12:$G$30,"No run") -> 0 | H32: =COUNTIF(UT25_Review_Rating_BVA!$G$12:$G$30,"Block") -> 0
A33: 26 | B33: UT26 – ReviewServiceImpl.submitReview – เงื่อนไขอื่น | C33: Weak Robust Equivalence Class Testing | D33: =COUNTA(UT26_Review_EC!$A$21:$A$30) -> 8 | E33: =COUNTIF(UT26_Review_EC!$F$21:$F$30,"Pass") -> 8 | F33: =COUNTIF(UT26_Review_EC!$F$21:$F$30,"Fail") -> 0 | G33: =COUNTIF(UT26_Review_EC!$F$21:$F$30,"No run") -> 0 | H33: =COUNTIF(UT26_Review_EC!$F$21:$F$30,"Block") -> 0
A34: Auth & User
A35: 27 | B35: UT27 – AuthServiceImpl.login | C35: Decision Table (Limited Entry) | D35: =COUNTA(UT27_Login_DT!$B$22:$B$28) -> 6 | E35: =COUNTIF(UT27_Login_DT!$H$22:$H$28,"Pass") -> 6 | F35: =COUNTIF(UT27_Login_DT!$H$22:$H$28,"Fail") -> 0 | G35: =COUNTIF(UT27_Login_DT!$H$22:$H$28,"No run") -> 0 | H35: =COUNTIF(UT27_Login_DT!$H$22:$H$28,"Block") -> 0
A36: 28 | B36: UT28 – AuthServiceImpl.register | C36: Weak Robust Equivalence Class Testing | D36: =COUNTA(UT28_Register_EC!$A$19:$A$23) -> 4 | E36: =COUNTIF(UT28_Register_EC!$G$19:$G$23,"Pass") -> 4 | F36: =COUNTIF(UT28_Register_EC!$G$19:$G$23,"Fail") -> 0 | G36: =COUNTIF(UT28_Register_EC!$G$19:$G$23,"No run") -> 0 | H36: =COUNTIF(UT28_Register_EC!$G$19:$G$23,"Block") -> 0
A37: 29 | B37: UT29 – UserServiceImpl.updateProfile | C37: Decision Table (Limited Entry) | D37: =COUNTA(UT29_UpdateProfile_DT!$B$28:$B$35) -> 7 | E37: =COUNTIF(UT29_UpdateProfile_DT!$H$28:$H$35,"Pass") -> 7 | F37: =COUNTIF(UT29_UpdateProfile_DT!$H$28:$H$35,"Fail") -> 0 | G37: =COUNTIF(UT29_UpdateProfile_DT!$H$28:$H$35,"No run") -> 0 | H37: =COUNTIF(UT29_UpdateProfile_DT!$H$28:$H$35,"Block") -> 0
A38: 30 | B38: UT30 – UserSessionServiceImpl – สถานะออนไลน์ (หน้าต่าง 15 นาที) | C38: Robustness Testing (ขอบด้านเดียว) | D38: =COUNTA(UT30_UserSession_BVA!$A$12:$A$19) -> 7 | E38: =COUNTIF(UT30_UserSession_BVA!$F$12:$F$19,"Pass") -> 7 | F38: =COUNTIF(UT30_UserSession_BVA!$F$12:$F$19,"Fail") -> 0 | G38: =COUNTIF(UT30_UserSession_BVA!$F$12:$F$19,"No run") -> 0 | H38: =COUNTIF(UT30_UserSession_BVA!$F$12:$F$19,"Block") -> 0
A39: 31 | B39: UT31 – JwtTokenProvider | C39: Weak Robust Equivalence Class Testing | D39: =COUNTA(UT31_JwtToken_EC!$A$21:$A$27) -> 6 | E39: =COUNTIF(UT31_JwtToken_EC!$F$21:$F$27,"Pass") -> 6 | F39: =COUNTIF(UT31_JwtToken_EC!$F$21:$F$27,"Fail") -> 0 | G39: =COUNTIF(UT31_JwtToken_EC!$F$21:$F$27,"No run") -> 0 | H39: =COUNTIF(UT31_JwtToken_EC!$F$21:$F$27,"Block") -> 0
A40: Admin resources
A41: 32 | B41: UT32 – RoomServiceImpl | C41: Weak Robust Equivalence Class Testing | D41: =COUNTA(UT32_RoomService_EC!$A$20:$A$26) -> 6 | E41: =COUNTIF(UT32_RoomService_EC!$F$20:$F$26,"Pass") -> 6 | F41: =COUNTIF(UT32_RoomService_EC!$F$20:$F$26,"Fail") -> 0 | G41: =COUNTIF(UT32_RoomService_EC!$F$20:$F$26,"No run") -> 0 | H41: =COUNTIF(UT32_RoomService_EC!$F$20:$F$26,"Block") -> 0
A42: 33 | B42: UT33 – ServiceCatalogServiceImpl | C42: Weak Robust Equivalence Class Testing (ใช้ค่าขอบเป็นตัวแทนคลาส) | D42: =COUNTA(UT33_ServiceCatalog_EC!$A$21:$A$29) -> 8 | E42: =COUNTIF(UT33_ServiceCatalog_EC!$G$21:$G$29,"Pass") -> 8 | F42: =COUNTIF(UT33_ServiceCatalog_EC!$G$21:$G$29,"Fail") -> 0 | G42: =COUNTIF(UT33_ServiceCatalog_EC!$G$21:$G$29,"No run") -> 0 | H42: =COUNTIF(UT33_ServiceCatalog_EC!$G$21:$G$29,"Block") -> 0
A43: 34 | B43: UT34 – TherapistServiceImpl.updateSchedule – กะทำงาน | C43: Robustness Testing (ขอบด้านเดียว) | D43: =COUNTA(UT34_Schedule_Shift_BVA!$A$12:$A$21) -> 9 | E43: =COUNTIF(UT34_Schedule_Shift_BVA!$F$12:$F$21,"Pass") -> 9 | F43: =COUNTIF(UT34_Schedule_Shift_BVA!$F$12:$F$21,"Fail") -> 0 | G43: =COUNTIF(UT34_Schedule_Shift_BVA!$F$12:$F$21,"No run") -> 0 | H43: =COUNTIF(UT34_Schedule_Shift_BVA!$F$12:$F$21,"Block") -> 0
A44: 35 | B44: UT35 – ShopServiceImpl.updateShop – เวลาเปิด–ปิด | C44: Robustness Testing (ขอบด้านเดียว) | D44: =COUNTA(UT35_ShopHours_BVA!$A$12:$A$19) -> 7 | E44: =COUNTIF(UT35_ShopHours_BVA!$F$12:$F$19,"Pass") -> 7 | F44: =COUNTIF(UT35_ShopHours_BVA!$F$12:$F$19,"Fail") -> 0 | G44: =COUNTIF(UT35_ShopHours_BVA!$F$12:$F$19,"No run") -> 0 | H44: =COUNTIF(UT35_ShopHours_BVA!$F$12:$F$19,"Block") -> 0
A45: Report
A46: 36 | B46: UT36 – ReportServiceImpl.getRevenueReport – ช่วงวันที่ | C46: Robustness Testing (ขอบด้านเดียว) | D46: =COUNTA(UT36_RevenueReport_BVA!$A$12:$A$21) -> 9 | E46: =COUNTIF(UT36_RevenueReport_BVA!$G$12:$G$21,"Pass") -> 9 | F46: =COUNTIF(UT36_RevenueReport_BVA!$G$12:$G$21,"Fail") -> 0 | G46: =COUNTIF(UT36_RevenueReport_BVA!$G$12:$G$21,"No run") -> 0 | H46: =COUNTIF(UT36_RevenueReport_BVA!$G$12:$G$21,"Block") -> 0
A47: Total | D47: {=SUMPRODUCT(ISNUMBER(D4:D46)*D4:D46)} -> 359 | E47: {=SUMPRODUCT(ISNUMBER(E4:E46)*E4:E46)} -> 356 | F47: {=SUMPRODUCT(ISNUMBER(F4:F46)*F4:F46)} -> 3 | G47: {=SUMPRODUCT(ISNUMBER(G4:G46)*G4:G46)} -> 0 | H47: {=SUMPRODUCT(ISNUMBER(H4:H46)*H4:H46)} -> 0

Sheet Defect Summary
A1: No | B1: Defect No | C1: Defect Title | D1: Report Date | E1: Fix date | F1: Reporter | G1: Defect Status | H1: Defect Severity | I1: Defect Priority | J1: Closed By | K1: Defect Details
A2: 1 | B2: DEF-001 | C2: จองหมอนวดนอกกะทำงานได้ (ตรวจแค่ isDayOff) | D2: 09/10/2026 | E2: 46305 | F2: Piyachayanin | G2: Open | H2: High | I2: High | J2: Piyachayanin | K2: service/impl/BookingServiceImpl.java และ AvailabilityServiceImpl.java ไม่เทียบ WorkShift • ผิด UC-08b • UT02-TC002
A3: 2 | B3: DEF-002 | C3: createBooking ไม่ตรวจเวลา: จองย้อนหลัง, จองกระชั้นกว่า 30 นาที, เกิน 14 วัน, นอกเวลาทำการได้ | D3: 09/10/2026 | E3: 46305 | F3: Piyachayanin | G3: Open | H3: High | I3: High | J3: Piyachayanin | K3: service/impl/BookingServiceImpl.java startDateTime ≠ null • ผิด BR-BKG-02, BR-BKG-03 • UT03-TC002, TC007, TC008, TC013
A4: 3 | B4: DEF-003 | C4: ยกเลิก booking ที่จ่ายเงินแล้วไม่ส่งเข้ากระบวนการคืนเงิน | D4: 09/10/2026 | E4: 46305 | F4: Piyachayanin | G4: Open | H4: Medium | I4: Medium | J4: Piyachayanin | K4: service/impl/BookingServiceImpl.java cancelBooking (บรรทัด 270–300) • ผิด UC-10 A1 • UT05-TC007
A5: 4 | B5: DEF-004 | C5: cancelBooking / updateBookingStatus ไม่ publish BookingStatusChangedEvent | D5: 09/10/2026 | E5: 46305 | F5: Piyachayanin | G5: Open | H5: Low | I5: Medium | J5: Piyachayanin | K5: service/impl/BookingServiceImpl.java • Observer (NotificationListener, QueueListener) ไม่ทำงานเมื่อเปลี่ยนสถานะผ่าน 2 เมธอดนี้ • UT05-TC005
A6: 5 | B6: DEF-005 | C6: เปลี่ยนเป็น NO_SHOW ได้ทันทีโดยไม่ตรวจว่าเลยเวลานัด 15 นาที | D6: 09/10/2026 | E6: 46305 | F6: Piyachayanin | G6: Open | H6: Medium | I6: Medium | J6: Piyachayanin | K6: service/impl/BookingServiceImpl.java ConfirmedState.markNoShow • ผิด BR-BKG-05 • UT08 เคสสุดท้าย
A7: 6 | B7: DEF-006 | C7: checkAvailability คืนรอบเวลาผิดเมื่อ durationMinutes ยาวจนเวลาวนข้ามเที่ยงคืน | D7: 09/10/2026 | E7: 46305 | F7: Piyachayanin | G7: Open | H7: Low | I7: Low | J7: Piyachayanin | K7: service/impl/AvailabilityServiceImpl.java บรรทัด 129 ใช้ LocalTime.plusMinutes ซึ่งวนรอบ 24 ชม. • durationMinutes มาจาก query parameter สาธารณะ • UT10-TC008
A8: 7 | B8: DEF-007 | C8: Booking ที่ COMPLETED ยังล็อกห้องและหมอนวด | D8: 09/10/2026 | E8: 46305 | F8: Piyachayanin | G8: Open | H8: Low | I8: Low | J8: Piyachayanin | K8: service/impl/BookingServiceImpl.java และ AvailabilityServiceImpl.java : EXCLUDED_STATUSES มีแค่ CANCELLED, NO_SHOW • UC-08 ข้อ 4 ระบุว่า COMPLETED ไม่ใช่ active • UT11-TC006
A9: 8 | B9: DEF-008 | C9: ชำระเงินตอน CHECKED_IN แล้ว Booking กลายเป็น COMPLETED (ข้าม IN_SERVICE) | D9: 09/10/2026 | F9: Piyachayanin | G9: Open | H9: High | I9: High | K9: service/impl/PaymentServiceImpl.java ผิด BR-QUE-03 และ State diagram • ข้าม completeService() ห้องไม่เข้า CLEANING, คิวไม่ COMPLETED • ยืนยันด้วย UT14-TC009
A10: 9 | B10: DEF-009 | C10: เปลี่ยนสถานะ Booking ตอนชำระเงินแต่ไม่ publish BookingStatusChangedEvent | D10: 09/10/2026 | F10: Piyachayanin | G10: Open | H10: Medium | I10: Medium | K10: service/impl/PaymentServiceImpl.java (ไม่มี ApplicationEventPublisher) • ลูกค้าไม่ได้รับแจ้งเตือน (UC-07 ข้อ 13) • UT14-TC007, TC008
A11: 10 | B11: DEF-010 | C11: รับชำระเงินของ Booking ที่ CANCELLED / NO_SHOW ได้ | D11: 09/10/2026 | F11: Piyachayanin | G11: Open | H11: Medium | I11: Medium | K11: service/impl/PaymentServiceImpl.java processPayment ไม่ตรวจสถานะ booking • ผิด SRS 7.1 (end state) • UT14-TC010, TC011
A12: 11 | B12: DEF-011 | C12: ผู้ใช้คนใดก็รีวิว booking ของคนอื่นได้ | D12: 09/10/2026 | F12: Piyachayanin | G12: Open | H12: Medium | I12: Medium | K12: service/impl/ReviewServiceImpl.submitReview และ ReviewController ไม่รับ/ไม่ตรวจผู้ใช้ปัจจุบัน • ผิด BR-SEC-01 • UT26-TC010

Sheet UT01_CreateBooking_EC
A1: Equivalence Class Design
A2: Valid EC | F2: Invalid EC
A3: EC ID | B3: Condition | F3: EC ID | G3: Condition
A4: V1 | B4: currentUser เป็น CUSTOMER และมีโปรไฟล์ Customer | F4: I1 | G4: currentUser = null
A5: V2 | B5: currentUser เป็น RECEPTIONIST/OWNER และระบุ customerId ที่มีอยู่ | F5: I2 | G5: CUSTOMER แต่ไม่พบโปรไฟล์ Customer
A6: V3 | B6: serviceId มีอยู่ และ isActive = true | F6: I3 | G6: พนักงานไม่ระบุ customerId
A7: V4 | B7: durationOptionId มีอยู่, active และเป็นของ service ที่เลือก | F7: I4 | G7: พนักงานระบุ customerId ที่ไม่มีอยู่
A8: V5 | B8: startDateTime ไม่เป็น null | F8: I5 | G8: serviceId ไม่มีอยู่
A9: V6 | B9: therapistId = null (ระบบจัดสรร) หรือหมอนวด active ที่มีทักษะ | F9: I6 | G9: service isActive = false
F10: I7 | G10: durationOptionId ไม่มีอยู่
F11: I8 | G11: durationOption เป็นของ service อื่น
F12: I9 | G12: durationOption isActive = false
F13: I10 | G13: startDateTime = null
F14: I11 | G14: therapistId ไม่มีอยู่
F15: I12 | G15: หมอนวด isActive = false
F16: I13 | G16: หมอนวดไม่มีทักษะบริการนี้
A18: Test Case Design and Test Results
A20: Project Name: | B20: BookingServiceImpl.createBooking – ข้อมูลนำเข้าและผู้ทำรายการ | I20: Student ID: | J20: 673380049-4
A21: Test Strategy: | B21: Functional testing - Weak Robust Equivalence Class Testing | I21: Designer: | J21: Piyachayanin
A22: Test Environtment: | B22: Lenovo LOQ 15AHP11, CPU AMD Ryzen 7 250, Memory 16 GB DDR5, GPU NVIDIA GeForce RTX 5050 Laptop, OS Window 11 | I22: Date: | J22: 09/10/2026
A23: Method under test: | B23: BookingResponseDTO createBooking(BookingRequestDTO requestDTO, User currentUser)
A24: Requirement อ้างอิง: | B24: UC-07 Preconditions • BR-RES-04 • SRS 3.3
A26: Test Case ID | B26: Input | H26: Expected Result | I26: Actual Result | J26: Status (Pass/Fail/No run)
B27: currentUser | C27: customerId | D27: serviceId | E27: durationOptionId | F27: therapistId | G27: startDateTime
A28: UT01-TC001 | B28: Customer#1 | C28: − | D28: 1 | E28: 11 | F28: 5 | G28: 09/11 15:30 | H28: (V1,V3–V6) สร้างสำเร็จ: status = PENDING, bookingChannel = ONLINE, totalPrice = 600.00, end = 16:30, therapist = T5, room เป็นห้อง SINGLE, bookingReferenceCode รูปแบบ BK-yyyyMMdd-XXXXXX, save ถูกเรียก 1 ครั้ง | I28: (V1,V3–V6) สร้างสำเร็จ: status = PENDING, bookingChannel = ONLINE, totalPrice = 600.00, end = 16:30, therapist = T5, room เป็นห้อง SINGLE, bookingReferenceCode รูปแบบ BK-yyyyMMdd-XXXXXX, save ถูกเรียก 1 ครั้ง | J28: Pass
A29: UT01-TC002 | B29: Receptionist#50 | C29: 1 | D29: 1 | E29: 11 | F29: null | G29: 09/11 15:30 | H29: (V2,V6) สร้างสำเร็จ: status = CONFIRMED, bookingChannel = WALK_IN, therapist ถูกจัดสรรอัตโนมัติและมีทักษะ S1 | I29: (V2,V6) สร้างสำเร็จ: status = CONFIRMED, bookingChannel = WALK_IN, therapist ถูกจัดสรรอัตโนมัติและมีทักษะ S1 | J29: Pass
A30: UT01-TC003 | B30: null | C30: − | D30: 1 | E30: 11 | F30: 5 | G30: 09/11 15:30 | H30: BusinessException 401 | I30: BusinessException 401 | J30: Pass
A31: UT01-TC004 | B31: Customer#9 (ไม่มีโปรไฟล์) | C31: − | D31: 1 | E31: 11 | F31: 5 | G31: 09/11 15:30 | H31: NotFoundException | I31: NotFoundException | J31: Pass
A32: UT01-TC005 | B32: Receptionist#50 | C32: null | D32: 1 | E32: 11 | F32: 5 | G32: 09/11 15:30 | H32: ValidationException "Customer ID is required..." | I32: ValidationException | J32: Pass
A33: UT01-TC006 | B33: Receptionist#50 | C33: 999 | D33: 1 | E33: 11 | F33: 5 | G33: 09/11 15:30 | H33: NotFoundException | I33: NotFoundException | J33: Pass
A34: UT01-TC007 | B34: Customer#1 | C34: − | D34: 999 | E34: 11 | F34: 5 | G34: 09/11 15:30 | H34: NotFoundException | I34: NotFoundException | J34: Pass
A35: UT01-TC008 | B35: Customer#1 | C35: − | D35: 3 | E35: 31 | F35: 5 | G35: 09/11 15:30 | H35: ValidationException "Selected service is inactive" | I35: ValidationException | J35: Pass
A36: UT01-TC009 | B36: Customer#1 | C36: − | D36: 1 | E36: 999 | F36: 5 | G36: 09/11 15:30 | H36: NotFoundException | I36: NotFoundException | J36: Pass
A37: UT01-TC010 | B37: Customer#1 | C37: − | D37: 1 | E37: 21 | F37: 5 | G37: 09/11 15:30 | H37: ValidationException "Duration option does not belong..." | I37: ValidationException | J37: Pass
A38: UT01-TC011 | B38: Customer#1 | C38: − | D38: 1 | E38: 12 | F38: 5 | G38: 09/11 15:30 | H38: ValidationException "Selected duration option is inactive" | I38: ValidationException | J38: Pass
A39: UT01-TC012 | B39: Customer#1 | C39: − | D39: 1 | E39: 11 | F39: 5 | G39: null | H39: ValidationException "Start date time is required" | I39: ValidationException | J39: Pass
... A42: UT01-TC015 | B42: Customer#1 | C42: − | D42: 1 | E42: 11 | F42: 6 | G42: 09/11 15:30 | H42: ValidationException "...does not possess the skill..." | I42: ValidationException | J42: Pass

Sheet UT02_CreateBooking_DT
A1: Condition | B1: Rule#1 | C1: Rule#2 | D1: Rule#3 | E1: Rule#4 | F1: Rule#5 | G1: Rule#6 | H1: Rule#7 | I1: Rule#8
A2: C1: ระบุ therapistId | B2: Y | C2: Y | D2: N | E2: Y | F2: Y | G2: Y | H2: N | I2: N
A3: C2: หมอนวดที่ระบุไม่พร้อม (isDayOff หรือเวลาจองอยู่นอกกะ) | B3: Y | C3: N | D3: − | E3: N | F3: N | G3: N | H3: − | I3: −
A4: C3: หมอนวดที่ระบุมีคิวทับ | B4: − | C4: Y | D4: − | E4: N | F4: N | G4: N | H4: − | I4: −
A5: C4: (ไม่ระบุ) มีหมอนวดที่มีทักษะ ไม่หยุด และว่าง ≥ 1 คน | B5: − | C5: − | D5: N | E5: − | F5: − | G5: − | H5: Y | I5: Y
A6: C5: ระบุ roomId | B6: − | C6: − | D6: − | E6: Y | F6: Y | G6: Y | H6: N | I6: N
A7: C6: ห้องที่ระบุ active และประเภทตรงบริการ | B7: − | C7: − | D7: − | E7: N | F7: Y | G7: Y | H7: − | I7: −
A8: C7: ห้องที่ระบุ/ห้องผู้สมัครว่าง (รวม buffer) | B8: − | C8: − | D8: − | E8: − | F8: N | G8: Y | H8: N | I8: Y
A9: Action
A10: A1: ConflictException หมอนวดหยุด/นอกกะ | B10: X
A11: A2: ConflictException หมอนวดไม่ว่าง | C11: X
A12: A3: ConflictException ไม่มีหมอนวดว่าง | D12: X
A13: A4: ValidationException ห้องปิด/ประเภทไม่ตรง | E13: X
A14: A5: ConflictException ห้องไม่ว่าง/ไม่มีห้องว่าง | F14: X | H14: X
A15: A6: save Booking พร้อม therapist + room | G15: X | I15: X
A16: Impossible
A17: ทุก rule ที่ไม่ใช่ A6 ต้องไม่เรียก bookingRepository.save
A19: Test Case Design and Test Results
A21: Project Name: | B21: BookingServiceImpl.createBooking – จัดสรรหมอนวดและห้อง | H21: Student ID: | I21: 673380049-4
A22: Test Strategy: | B22: Functional testing - Decision Table (Limited Entry) | H22: Designer: | I22: Piyachayanin
A23: Test Environtment: | B23: Lenovo LOQ 15AHP11, CPU AMD Ryzen 7 250, Memory 16 GB DDR5, GPU NVIDIA GeForce RTX 5050 Laptop, OS Window 11 | H23: Date: | I23: 09/10/2026
A24: Method under test: | B24: createBooking(...) ส่วนที่ 3 (หมอนวด) และ 4 (ห้อง + cleaning buffer 15 นาที)
A25: Requirement อ้างอิง: | B25: UC-07 A1, E2, E3 • UC-08a/08b • BR-BKG-01 • BR-RES-03 (buffer 15 นาที)
A27: Rule# | B27: Test Case ID | C27: Input | F27: Expected Result | G27: Actual Result | H27: Status (Pass/Fail/No run)
C28: therapistId | D28: roomId | E28: สภาพข้อมูล (mock)
A29: R1 | B29: UT02-TC001 | C29: 5 | D29: null | E29: T5 isDayOff = true วันที่ 09/11 | F29: ConflictException | G29: ConflictException | H29: Pass
A30: R1 | B30: UT02-TC002 | C30: 5 | D30: null | E30: T5 มีกะ 10:00–14:00 แต่จอง 15:30–16:30 | F30: ConflictException หมอนวดนอกกะ | G30: ConflictException หมอนวดนอกกะ | H30: Pass
A31: R2 | B31: UT02-TC003 | C31: 5 | D31: null | E31: T5 มีคิว 15:00–16:00 สถานะ CONFIRMED | F31: ConflictException "...already booked..." | G31: ConflictException | H31: Pass
A32: R3 | B32: UT02-TC004 | C32: null | D32: null | E32: ผู้มีทักษะ S1 มีแค่ T5, T8 — T5 หยุด, T8 มีคิวทับ | F32: ConflictException "No therapists available..." | G32: ConflictException | H32: Pass
A33: R4 | B33: UT02-TC005 | C33: 5 | D33: 201 (COUPLE) | E33: T5 ว่าง | F33: ValidationException "Selected room type COUPLE is not suitable..." | G33: ValidationException | H33: Pass
A34: R4 | B34: UT02-TC006 | C34: 5 | D34: 103 (inactive) | E34: T5 ว่าง | F34: ValidationException "Selected room is inactive" | G34: ValidationException | H34: Pass
A35: R5 | B35: UT02-TC007 | C35: 5 | D35: 101 | E35: R101 มีคิว 14:00–15:20 | F35: ConflictException "Room R101 is occupied or undergoing cleaning buffer..." | G35: ConflictException | H35: Pass
A36: R6 | B36: UT02-TC008 | C36: 5 | D36: 102 | E36: T5 และ R102 ว่าง | F36: สำเร็จ: therapist = T5, room = R102 | G36: สำเร็จ: therapist = T5, room = R102 | H36: Pass
A37: R7 | B37: UT02-TC009 | C37: null | D37: null | E37: T8 ว่าง • R101, R102 ไม่ว่าง | F37: ConflictException "No suitable rooms available..." | G37: ConflictException | H37: Pass
A38: R8 | B38: UT02-TC010 | C38: null | D38: null | E38: T5 หยุด, T8 ว่าง • R101 ไม่ว่าง, R102 ว่าง | F38: สำเร็จ: therapist = T8 (ข้ามคนที่หยุด), room = R102 (ข้ามห้องไม่ว่างและห้อง COUPLE) | G38: สำเร็จ: therapist = T8 , room = R102 | H38: Pass

Sheet UT03_CreateBooking_Time_BVA
A1: Test Case Design and Test Results | K1: lead (นาทีล่วงหน้า) | L1: เวลาเริ่ม (บริการ 60 นาที)
J2: min- | K2: 29 | L2: 09:59
A3: Project Name: | B3: BookingServiceImpl.createBooking – ช่วงเวลาที่จองได้ | F3: Student ID: | G3: 673380049-4 | J3: min | K3: 30 | L3: 10:00
A4: Test Strategy: | B4: Functional testing - Robustness Testing | F4: Designer: | G4: Piyachayanin | J4: min+ | K4: 31 | L4: 10:01
A5: Test Environtment: | B5: Lenovo LOQ 15AHP11, CPU AMD Ryzen 7 250, Memory 16 GB DDR5, GPU NVIDIA GeForce RTX 5050 Laptop, OS Window 11 | F5: Date: | G5: 09/10/2026 | J5: nom | K5: 10110 | L5: 15:30
A6: Method under test: | B6: createBooking(...) – เงื่อนไขของ startDateTime | J6: max- | K6: 20159 | L6: 20:59
A7: Requirement อ้างอิง: | B7: BR-BKG-02 Operating Hours • BR-BKG-03 (ล่วงหน้า ≥ 30 นาที) • SRS 3.3 Step 2 (สูงสุด 14 วัน) • ดู Q2 | J7: max+ | K7: 20161 | L7: 21:01
A9: Test Case ID | B9: Input | E9: Expected Result | F9: Actual Result | G9: Status (Pass/Fail/No run)
B10: startDateTime | C10: lead (นาที) | D10: เวลาเริ่ม
A11: UT03-TC001 | B11: 2026-11-09 15:30 | C11: 10110 | D11: 15:30 | E11: สร้างสำเร็จ status = PENDING | F11: สร้างสำเร็จ | G11: Pass
A12: UT03-TC002 | B12: 2026-11-02 15:29 | C12: 29 | D12: 15:29 | E12: ValidationException ต้องจองล่วงหน้าอย่างน้อย 30 นาที | F12: สร้างสำเร็จ | G12: Pass
A13: UT03-TC003 | B13: 2026-11-02 15:30 | C13: 30 | D13: 15:30 | E13: สร้างสำเร็จ | F13: สร้างสำเร็จ | G13: Pass
A14: UT03-TC004 | B14: 2026-11-02 15:31 | C14: 31 | D14: 15:31 | E14: สร้างสำเร็จ | F14: สร้างสำเร็จ | G14: Pass
A15: UT03-TC005 | B15: 2026-11-16 14:59 | C15: 20159 | D15: 14:59 | E15: สร้างสำเร็จ | F15: สร้างสำเร็จ | G15: Pass
A16: UT03-TC006 | B16: 2026-11-16 15:00 | C16: 20160 | D16: 15:00 | E16: สร้างสำเร็จ | F16: สร้างสำเร็จ | G16: Pass
A17: UT03-TC007 | B17: 2026-11-16 15:01 | C17: 20161 | D17: 15:01 | E17: ValidationException จองล่วงหน้าได้ไม่เกิน 14 วัน | F17: สร้างสำเร็จ | G17: Pass
A18: UT03-TC008 | B18: 2026-11-09 09:59 | C18: 9779 | D18: 09:59 | E18: ValidationException เริ่มก่อนร้านเปิด | F18: สร้างสำเร็จ | G18: Pass
A19: UT03-TC009 | B19: 2026-11-09 10:00 | C19: 9780 | D19: 10:00 | E19: สร้างสำเร็จ | F19: สร้างสำเร็จ | G19: Pass
A20: UT03-TC010 | B20: 2026-11-09 10:01 | C20: 9781 | D20: 10:01 | E20: สร้างสำเร็จ | F20: สร้างสำเร็จ | G20: Pass
A21: UT03-TC011 | B21: 2026-11-09 20:59 | C21: 10439 | D21: 20:59 | E21: สร้างสำเร็จ | F21: สร้างสำเร็จ | G21: Pass
A22: UT03-TC012 | B22: 2026-11-09 21:00 | C22: 10440 | D22: 21:00 | E22: สร้างสำเร็จ (จบ 22:00 พอดี) | F22: สร้างสำเร็จ | G22: Pass
A23: UT03-TC013 | B23: 2026-11-09 21:01 | C23: 10441 | D23: 21:01 | E23: ValidationException จบ 22:01 เกินเวลาปิดร้าน | F23: สร้างสำเร็จ | G23: Pass

Sheet UT04_Overlap_Buffer_BVA
A1: Test Case Design and Test Results | L1: ห้อง: end เดิม→start ใหม่ | M1: ห้อง: end ใหม่→start เดิม | N1: หมอนวด: end เดิม→start ใหม่ | O1: หมอนวด: end ใหม่→start เดิม
K2: ขอบ-1 | L2: 14 | M2: 14 | N2: -1 | O2: -1
A3: Project Name: | B3: BookingRepository.findConflictingRoomBookingsWithCleaningBuffer + createBooking – เวลาทับซ้อน | G3: Student ID: | H3: 673380049-4 | K3: ขอบ | L3: 15 | M3: 15 | N3: 0 | O3: 0
A4: Test Strategy: | B4: Functional testing - Robustness Testing (ขอบด้านเดียว) | G4: Designer: | H4: Piyachayanin | K4: ขอบ+1 | L4: 16 | M4: 16 | N4: 1 | O4: 1
A5: Test Environtment: | B5: Lenovo LOQ 15AHP11, CPU AMD Ryzen 7 250, Memory 16 GB DDR5, GPU NVIDIA GeForce RTX 5050 Laptop, OS Window 11 | G5: Date: | H5: 09/10/2026 | K5: nom | L5: 120 | M5: − | N5: − | O5: −
A6: Method under test: | B6: default findConflictingRoomBookingsWithCleaningBuffer(roomId, start, end, 15, excluded) และ findConflictingTherapistBookings(...)
A7: Requirement อ้างอิง: | B7: BR-BKG-01 • BR-RES-03 • UC 6.1–6.2
A9: Test Case ID | B9: Input | F9: Expected Result | G9: Actual Result | H9: Status (Pass/Fail/No run)
B10: ทรัพยากร | C10: start ใหม่ | D10: end ใหม่ | E10: ระยะห่าง (นาที)
A11: UT04-TC001 | B11: R101 + T1 | C11: 16:00 | D11: 17:00 | E11: 120 | F11: จองสำเร็จ (nom) | G11: จองสำเร็จ | H11: Pass
A12: UT04-TC002 | B12: ห้อง R101 | C12: 14:14 | D12: 15:14 | E12: 14 | F12: ConflictException ห้องไม่ว่าง (ยังอยู่ใน buffer) | G12: ConflictException | H12: Pass
A13: UT04-TC003 | B13: ห้อง R101 | C13: 14:15 | D13: 15:15 | E13: 15 | F13: จองสำเร็จ | G13: จองสำเร็จ | H13: Pass
A14: UT04-TC004 | B14: ห้อง R101 | C14: 14:16 | D14: 15:16 | E14: 16 | F14: จองสำเร็จ | G14: จองสำเร็จ | H14: Pass
A15: UT04-TC005 | B15: ห้อง R101 | C15: 11:46 | D15: 12:46 | E15: 14 | F15: ConflictException ห้องไม่ว่าง | G15: ConflictException | H15: Pass
A16: UT04-TC006 | B16: ห้อง R101 | C16: 11:45 | D16: 12:45 | E16: 15 | F16: จองสำเร็จ | G16: จองสำเร็จ | H16: Pass
A17: UT04-TC007 | B17: ห้อง R101 | C17: 11:44 | D17: 12:44 | E17: 16 | F17: จองสำเร็จ | G17: จองสำเร็จ | H17: Pass
A18: UT04-TC008 | B18: หมอนวด T1 | C18: 13:59 | D18: 14:59 | E18: -1 | F18: ConflictException หมอนวดไม่ว่าง | G18: ConflictException | H18: Pass
A19: UT04-TC009 | B19: หมอนวด T1 | C19: 14:00 | D19: 15:00 | E19: 0 | F19: จองสำเร็จ | G19: จองสำเร็จ | H19: Pass
A20: UT04-TC010 | B20: หมอนวด T1 | C20: 14:01 | D20: 15:01 | E20: 1 | F20: จองสำเร็จ | G20: จองสำเร็จ | H20: Pass
A21: UT04-TC011 | B21: หมอนวด T1 | C21: 12:01 | D21: 13:01 | E21: -1 | F21: ConflictException หมอนวดไม่ว่าง | G21: ConflictException | H21: Pass
A22: UT04-TC012 | B22: หมอนวด T1 | C22: 12:00 | D22: 13:00 | E22: 0 | F22: จองสำเร็จ | G22: จองสำเร็จ | H22: Pass
A23: UT04-TC013 | B23: หมอนวด T1 | C23: 11:59 | D23: 12:59 | E23: 1 | F23: จองสำเร็จ | G23: จองสำเร็จ | H23: Pass

Sheet UT05_CancelBooking_DT
A1: Equivalence class
A2: EC1 (ผู้ใช้) = { null, CUSTOMER, STAFF (RECEPTIONIST/OWNER) }
A3: EC2 (สถานะ) = { PC = PENDING/CONFIRMED, CI = CHECKED_IN, END = IN_SERVICE/COMPLETED/CANCELLED/NO_SHOW }
A4: EC3 (เวลาก่อนเริ่ม) = { ≥ 2 ชม., < 2 ชม. }
A6: Condition | B6: Rule#1 | C6: Rule#2 | D6: Rule#3 | E6: Rule#4 | F6: Rule#5 | G6: Rule#6 | H6: Rule#7 | I6: Rule#8 | J6: Rule#9 | K6: Rule#10
A7: C1: currentUser | B7: null | C7: − | D7: CUST | E7: CUST | F7: CUST | G7: CUST | H7: CUST | I7: STAFF | J7: STAFF | K7: STAFF
A8: C2: พบ booking | B8: − | C8: N | D8: Y | E8: Y | F8: Y | G8: Y | H8: Y | I8: Y | J8: Y | K8: Y
A9: C3: เป็นเจ้าของ booking | B9: − | C9: − | D9: N | E9: Y | F9: Y | G9: Y | H9: Y | I9: − | J9: − | K9: −
A10: C4: เวลาก่อนเริ่ม | B10: − | C10: − | D10: − | E10: < 2 | F10: ≥ 2 | G10: ≥ 2 | H10: ≥ 2 | I10: < 2 | J10: − | K10: −
A11: C5: สถานะ | B11: − | C11: − | D11: − | E11: − | F11: PC | G11: PC | H11: END | I11: PC | J11: CI | K11: END
A12: C6: ชำระเงินแล้ว | B12: − | C12: − | D12: − | E12: − | F12: N | G12: Y | H12: − | I12: − | J12: − | K12: −
A13: Action
A14: A1: BusinessException 401 | B14: X
A15: A2: NotFoundException | C15: X
A16: A3: BusinessException 403 | D16: X
A17: A4: ValidationException ยกเลิกกระชั้นชิด | E17: X
A18: A5: ValidationException สถานะยกเลิกไม่ได้ (State) | H18: X | K18: X
A19: A6: status = CANCELLED + บันทึกเหตุผลใน specialNotes | F19: X | G19: X | I19: X | J19: X
A20: A7: ส่งคืนเงินเต็มจำนวน (RefundService) | G20: X
A21: Impossible
A22: R1 = null ทำงานก่อนค้นหา booking (โค้ดตรวจ currentUser ก่อน) • A5 มาจาก AbstractBookingState.throwInvalidTransition
A24: Test Case Design and Test Results
A26: Project Name: | B26: BookingServiceImpl.cancelBooking – ยกเลิกการจอง | J26: Student ID: | K26: 673380049-4
A27: Test Strategy: | B27: Functional testing - Decision Table (Extended Entry) | J27: Designer: | K27: Piyachayanin
A28: Test Environtment: | B28: Lenovo LOQ 15AHP11, CPU AMD Ryzen 7 250, Memory 16 GB DDR5, GPU NVIDIA GeForce RTX 5050 Laptop, OS Window 11 | J28: Date: | K28: 09/10/2026
A29: Method under test: | B29: BookingResponseDTO cancelBooking(Long id, CancelBookingRequestDTO dto, User currentUser)
A30: Requirement อ้างอิง: | B30: UC-10 (Main, A1, E1) • BR-BKG-04 • BR-SEC-01 • UC-5.1 • ดู Q3
A32: Rule# | B32: Test Case ID | C32: Input | G32: Expected Result | H32: Actual Result | I32: Status (Pass/Fail/No run)
C33: bookingId | D33: currentUser | E33: สถานะ / start | F33: dto.reason / Payment
A34: R1 | B34: UT05-TC001 | C34: 10 | D34: null | E34: CONFIRMED / 03/11 15:00 | F34: − | G34: BusinessException 401 | H34: BusinessException 401 | I34: Pass
A35: R2 | B35: UT05-TC002 | C35: 999 | D35: Customer#1 | E35: − | F35: − | G35: NotFoundException | H35: NotFoundException | I35: Pass
A36: R3 | B36: UT05-TC003 | C36: 10 | D36: Customer#2 | E36: CONFIRMED / 03/11 15:00 | F36: − | G36: BusinessException 403 • สถานะคง CONFIRMED • save ไม่ถูกเรียก | H36: BusinessException 403 | I36: Pass
A37: R4 | B37: UT05-TC004 | C37: 12 | D37: Customer#1 | E37: CONFIRMED / 02/11 16:00 (1 ชม.) | F37: − | G37: ValidationException "...at least 2 hours..." • สถานะคงเดิม | H37: ValidationException | I37: Pass
A38: R5 | B38: UT05-TC005 | C38: 13 | D38: Customer#1 | E38: PENDING / 03/11 15:00 | F38: reason = "ติดธุระ" / ไม่มี | G38: status = CANCELLED • specialNotes ลงท้าย "[Cancelled by CUSTOMER: ติดธุระ]" • save 1 ครั้ง | H38: CANCELLED | I38: Pass
A39: R5 | B39: UT05-TC006 | C39: 20 | D39: Customer#1 | E39: CONFIRMED / 03/11 15:00, notes เดิม "ปวดหลัง" | F39: dto = null / ไม่มี | G39: status = CANCELLED • specialNotes = "ปวดหลัง [Cancelled by CUSTOMER: Cancelled by user]" | H39: CANCELLED | I39: Pass
A40: R6 | B40: UT05-TC007 | C40: 14 | D40: Customer#1 | E40: CONFIRMED / 03/11 15:00 | F40: − / COMPLETED 600.00 | G40: status = CANCELLED และส่งคืนเงิน 600.00 | H40: COMPLETED | I40: Pass
A41: R7 | B41: UT05-TC008 | C41: 18 | D41: Customer#1 | E41: CANCELLED / 03/11 15:00 | F41: − | G41: ValidationException "Cannot execute action 'cancel' from booking status CANCELLED" | H41: ValidationException | I41: Pass
A42: R8 | B42: UT05-TC009 | C42: 15 | D42: Receptionist#50 | E42: CONFIRMED / 02/11 16:00 (1 ชม.) | F42: − | G42: status = CANCELLED (พนักงานไม่ติดกฎ 2 ชม.) • note "[Cancelled by RECEPTIONIST: ...]" | H42: CANCELLED | I42: Pass
A43: R9 | B43: UT05-TC010 | C43: 16 | D43: Owner#60 | E43: CHECKED_IN / 02/11 15:20 | F43: − | G43: status = CANCELLED (ยกเลิกฉุกเฉินหน้าร้าน) | H43: CANCELLED | I43: Pass
A44: R10 | B44: UT05-TC011 | C44: 17 | D44: Owner#60 | E44: COMPLETED / 02/11 10:00 | F44: − | G44: ValidationException • สถานะคง COMPLETED | H44: COMPLETED | I44: Pass
A45: R10 | B45: UT05-TC012 | C45: 21 | D45: Receptionist#50 | E45: IN_SERVICE / 02/11 14:30 | F45: − | G45: ValidationException • สถานะคง IN_SERVICE | H45: COMPLETED | I45: Pass

Sheet UT06_Cancel_2h_BVA
A1: Test Case Design and Test Results | J1: เวลาก่อนเริ่ม (นาที)
I2: นอกโดเมน | J2: -10
A3: Project Name: | B3: BookingServiceImpl.cancelBooking – กฎลูกค้ายกเลิกล่วงหน้า ≥ 2 ชั่วโมง | E3: Student ID: | F3: 673380049-4 | I3: ขอบ-1 | J3: 119
A4: Test Strategy: | B4: Functional testing - Robustness Testing (ขอบด้านเดียว) | E4: Designer: | F4: Piyachayanin | I4: ขอบ | J4: 120
A5: Test Environtment: | B5: Lenovo LOQ 15AHP11, CPU AMD Ryzen 7 250, Memory 16 GB DDR5, GPU NVIDIA GeForce RTX 5050 Laptop, OS Window 11 | E5: Date: | F5: 09/10/2026 | I5: ขอบ+1 | J5: 121
A6: Method under test: | B6: cancelBooking(...) | I6: nom | J6: 1440
A7: Requirement อ้างอิง: | B7: BR-BKG-04 • UC-10 E1
A9: Test Case ID | B9: Input | D9: Expected Result | E9: Actual Result | F9: Status (Pass/Fail/No run)
B10: start ของ booking | C10: เวลาก่อนเริ่ม (นาที)
A11: UT06-TC001 | B11: 2026-11-03 15:00 | C11: 1440 | D11: status = CANCELLED | E11: CANCELLED | F11: Pass
A12: UT06-TC002 | B12: 2026-11-02 16:59 | C12: 119 | D12: ValidationException ยกเลิกกระชั้นชิด • สถานะคง CONFIRMED | E12: ValidationException | F12: Pass
A13: UT06-TC003 | B13: 2026-11-02 17:00 | C13: 120 | D13: status = CANCELLED | E13: CANCELLED | F13: Pass
A14: UT06-TC004 | B14: 2026-11-02 17:01 | C14: 121 | D14: status = CANCELLED | E14: CANCELLED | F14: Pass
A15: UT06-TC005 | B15: 2026-11-02 14:50 | C15: -10 | D15: ValidationException • สถานะคง CONFIRMED | E15: ValidationException | F15: Pass

Sheet UT07_GetBookingById_DT
A1: Condition | B1: Rule#1 | C1: Rule#2 | D1: Rule#3 | E1: Rule#4 | F1: Rule#5 | G1: Rule#6 | H1: Rule#7
A2: C1: currentUser = null | B2: Y | C2: N | D2: N | E2: N | F2: N | G2: N | H2: N
A3: C2: พบ booking | B3: − | C3: N | D3: Y | E3: Y | F3: Y | G3: Y | H3: Y
A4: C3: role = CUSTOMER | B4: − | C4: − | D4: Y | E4: Y | F4: N | G4: N | H4: N
A5: C4: role = THERAPIST | B5: − | C5: − | D5: N | E5: N | F5: Y | G5: Y | H5: N
A6: C5: เป็นเจ้าของ / หมอนวดที่ได้รับมอบหมาย | B6: − | C6: − | D6: Y | E6: N | F6: Y | G6: N | H6: −
A7: Action
A8: A1: BusinessException 401 | B8: X
A9: A2: NotFoundException | C9: X
A10: A3: BusinessException 403 | E10: X | G10: X
A11: A4: คืน BookingResponseDTO | D11: X | F11: X | H11: X
A12: Impossible
A13: C3 และ C4 เป็น Y พร้อมกันไม่ได้ จึงไม่มี rule นั้น
A15: Test Case Design and Test Results
A17: Project Name: | B17: BookingServiceImpl.getBookingById – สิทธิ์การดูรายการจอง | G17: Student ID: | H17: 673380049-4
A18: Test Strategy: | B18: Functional testing - Decision Table (Limited Entry) | G18: Designer: | H18: Piyachayanin
A19: Test Environtment: | B19: Lenovo LOQ 15AHP11, CPU AMD Ryzen 7 250, Memory 16 GB DDR5, GPU NVIDIA GeForce RTX 5050 Laptop, OS Window 11 | G19: Date: | H19: 09/10/2026
A20: Method under test: | B20: BookingResponseDTO getBookingById(Long id, User currentUser)
A21: Requirement อ้างอิง: | B21: UC-09 • BR-SEC-01 • BR-SEC-02
A23: Rule# | B23: Test Case ID | C23: Input | E23: Expected Result | F23: Actual Result | G23: Status (Pass/Fail/No run)
C24: id | D24: currentUser
A25: R1 | B25: UT07-TC001 | C25: 10 | D25: null | E25: BusinessException 401 | F25: BusinessException 401 | G25: Pass
A26: R2 | B26: UT07-TC002 | C26: 999 | D26: Customer#1 | E26: NotFoundException | F26: NotFoundException | G26: Pass
A27: R3 | B27: UT07-TC003 | C27: 10 | D27: Customer#1 | E27: คืน DTO id = 10 | F27: คืน DTO id = 10 | G27: Pass
A28: R4 | B28: UT07-TC004 | C28: 10 | D28: Customer#2 | E28: BusinessException 403 | F28: BusinessException 403 | G28: Pass
A29: R5 | B29: UT07-TC005 | C29: 10 | D29: Therapist T5 | E29: คืน DTO id = 10 | F29: คืน DTO id = 10 | G29: Pass
A30: R6 | B30: UT07-TC006 | C30: 10 | D30: Therapist T8 | E30: BusinessException 403 | F30: BusinessException 403 | G30: Pass
A31: R6 | B31: UT07-TC007 | C31: 30 (therapist = null) | D31: Therapist T5 | E31: BusinessException 403 (ไม่เกิด NullPointerException) | F31: BusinessException 403 | G31: Pass
A32: R7 | B32: UT07-TC008 | C32: 10 | D32: Receptionist#50 | E32: คืน DTO id = 10 | F32: คืน DTO id = 10 | G32: Pass

Sheet UT08_BookingState_DT
A1: Equivalence class
A2: EC1 (สถานะปัจจุบัน) = { PENDING, CONFIRMED, CHECKED_IN, IN_SERVICE, COMPLETED, CANCELLED, NO_SHOW }
A3: EC2 (action) = { confirm, checkIn, startService, complete, cancel, markNoShow }
A4: ตารางด้านล่าง: แถว = action, คอลัมน์ Rule = สถานะปัจจุบัน, ช่อง = สถานะปลายทาง (✗ = ต้องโยน ValidationException)
A6: Condition | B6: Rule#1 | C6: Rule#2 | D6: Rule#3 | E6: Rule#4 | F6: Rule#5 | G6: Rule#6 | H6: Rule#7
A7: C1: สถานะปัจจุบัน | B7: PENDING | C7: CONFIRMED | D7: CHECKED_IN | E7: IN_SERVICE | F7: COMPLETED | G7: CANCELLED | H7: NO_SHOW
A8: C2 = confirm() | B8: → CONFIRMED | C8: ✗ | D8: ✗ | E8: ✗ | F8: ✗ | G8: ✗ | H8: ✗
A9: C2 = checkIn() | B9: ✗ | C9: → CHECKED_IN | D9: ✗ | E9: ✗ | F9: ✗ | G9: ✗ | H9: ✗
A10: C2 = startService() | B10: ✗ | C10: ✗ | D10: → IN_SERVICE | E10: ✗ | F10: ✗ | G10: ✗ | H10: ✗
A11: C2 = complete() | B11: ✗ | C11: ✗ | D11: ✗ | E11: → COMPLETED * | F11: ✗ | G11: ✗ | H11: ✗
A12: C2 = cancel() | B12: → CANCELLED | C12: → CANCELLED | D12: → CANCELLED | E12: ✗ | F12: ✗ | G12: ✗ | H12: ✗
A13: C2 = markNoShow() | B13: ✗ | C13: → NO_SHOW | D13: ✗ | E13: ✗ | F13: ✗ | G13: ✗ | H13: ✗
A14: Action
A15: A1: เปลี่ยนสถานะตามช่อง | B15: X | C15: X | D15: X | E15: X | F15: X | G15: X | H15: X
A16: A2: ✗ → ValidationException + สถานะคงเดิม | B16: X | C16: X | D16: X | E16: X | F16: X | G16: X | H16: X
A17: Impossible
A18: * complete() จาก IN_SERVICE ต้องมี Payment สถานะ COMPLETED
A20: Test Case Design and Test Results
A22: Project Name: | B22: Booking State Pattern (Booking.confirm/checkIn/startService/complete/cancel/markNoShow) | G22: Student ID: | H22: 673380049-4
A23: Test Strategy: | B23: Functional testing - Decision Table (Extended Entry) แบบ State Transition Table | G23: Designer: | H23: Piyachayanin
A24: Test Environtment: | B24: Lenovo LOQ 15AHP11, CPU AMD Ryzen 7 250, Memory 16 GB DDR5, GPU NVIDIA GeForce RTX 5050 Laptop, OS Window 11 | G24: Date: | H24: 09/10/2026
A25: Method under test: | B25: Booking.<action>() → BookingStateFactory.getState(status).<action>(booking) ใน pattern/state/*
A26: Requirement อ้างอิง: | B26: SRS 7.1 • UC §5, §5.1 • UC-14 • BR-QUE-03
A28: Rule# | B28: Test Case ID | C28: Input | F28: Expected Result | G28: Actual Result | H28: Status (Pass/Fail/No run)
C29: สถานะปัจจุบัน | D29: Action | E29: Payment
A30: PENDING/confirm() | B30: UT08-TC001 | C30: PENDING | D30: confirm() | E30: − | F30: status = CONFIRMED | H30: Pass
A31: PENDING/checkIn() | B31: UT08-TC002 | C31: PENDING | D31: checkIn() | E31: − | F31: ValidationException "Cannot execute action 'checkIn' from booking status PENDING" • สถานะคงเดิม | G31: ValidationException | H31: Pass
A32: PENDING/startService() | B32: UT08-TC003 | C32: PENDING | D32: startService() | E32: − | F32: ValidationException "Cannot execute action 'startService' from booking status PENDING" • สถานะคงเดิม | G32: ValidationException | H32: Pass
A33: PENDING/complete() | B33: UT08-TC004 | C33: PENDING | D33: complete() | E33: − | F33: ValidationException "Cannot execute action 'complete' from booking status PENDING" • สถานะคงเดิม | G33: ValidationException | H33: Pass
A34: PENDING/cancel() | B34: UT08-TC005 | C34: PENDING | D34: cancel() | E34: − | F34: status = CANCELLED | G34: CANCELLED | H34: Pass
A35: PENDING/markNoShow() | B35: UT08-TC006 | C35: PENDING | D35: markNoShow() | E35: − | F35: ValidationException "Cannot execute action 'markNoShow' from booking status PENDING" • สถานะคงเดิม | G35: ValidationException | H35: Pass
A36: CONFIRMED/confirm() | B36: UT08-TC007 | C36: CONFIRMED | D36: confirm() | E36: − | F36: ValidationException "Cannot execute action 'confirm' from booking status CONFIRMED" • สถานะคงเดิม | G36: ValidationException | H36: Pass
A37: CONFIRMED/checkIn() | B37: UT08-TC008 | C37: CONFIRMED | D37: checkIn() | E37: − | F37: status = CHECKED_IN | G37: CHECKED_IN | H37: Pass
A38: CONFIRMED/startService() | B38: UT08-TC009 | C38: CONFIRMED | D38: startService() | E38: − | F38: ValidationException "Cannot execute action 'startService' from booking status CONFIRMED" • สถานะคงเดิม | G38: ValidationException | H38: Pass
A39: CONFIRMED/complete() | B39: UT08-TC010 | C39: CONFIRMED | D39: complete() | E39: − | F39: ValidationException "Cannot execute action 'complete' from booking status CONFIRMED" • สถานะคงเดิม | G39: ValidationException | H39: Pass
A40: CONFIRMED/cancel() | B40: UT08-TC011 | C40: CONFIRMED | D40: cancel() | E40: − | F40: status = CANCELLED | G40: CANCELLED | H40: Pass
A41: CONFIRMED/markNoShow() | B41: UT08-TC012 | C41: CONFIRMED | D41: markNoShow() | E41: − | F41: status = NO_SHOW | G41: NO_SHOW | H41: Pass
A42: CHECKED_IN/confirm() | B42: UT08-TC013 | C42: CHECKED_IN | D42: confirm() | E42: − | F42: ValidationException "Cannot execute action 'confirm' from booking status CHECKED_IN" • สถานะคงเดิม | G42: ValidationException | H42: Pass
... A45: CHECKED_IN/complete() | B45: UT08-TC016 | C45: CHECKED_IN | D45: complete() | E45: − | F45: ValidationException "Cannot execute action 'complete' from booking status CHECKED_IN" • สถานะคงเดิม | G45: ValidationException | H45: Pass
A46: CHECKED_IN/cancel() | B46: UT08-TC017 | C46: CHECKED_IN | D46: cancel() | E46: − | F46: status = CANCELLED | H46: Pass
A47: CHECKED_IN/markNoShow() | B47: UT08-TC018 | C47: CHECKED_IN | D47: markNoShow() | E47: − | F47: ValidationException "Cannot execute action 'markNoShow' from booking status CHECKED_IN" • สถานะคงเดิม | G47: ValidationException | H47: Pass
A48: IN_SERVICE/confirm() | B48: UT08-TC019 | C48: IN_SERVICE | D48: confirm() | E48: − | F48: ValidationException "Cannot execute action 'confirm' from booking status IN_SERVICE" • สถานะคงเดิม | G48: ValidationException | H48: Pass
A49: IN_SERVICE/checkIn() | B49: UT08-TC020 | C49: IN_SERVICE | D49: checkIn() | E49: − | F49: ValidationException "Cannot execute action 'checkIn' from booking status IN_SERVICE" • สถานะคงเดิม | G49: ValidationException | H49: Pass
A50: IN_SERVICE/startService() | B50: UT08-TC021 | C50: IN_SERVICE | D50: startService() | E50: − | F50: ValidationException "Cannot execute action 'startService' from booking status IN_SERVICE" • สถานะคงเดิม | G50: ValidationException | H50: Pass
A51: IN_SERVICE/complete() | B51: UT08-TC022 | C51: IN_SERVICE | D51: complete() | E51: COMPLETED | F51: status = COMPLETED และตั้ง actualEndTime | G51: COMPLETED | H51: Pass
A52: IN_SERVICE/complete() | B52: UT08-TC023 | C52: IN_SERVICE | D52: complete() | E52: PENDING หรือไม่มี | F52: ValidationException ต้องชำระเงินก่อน • สถานะคง IN_SERVICE | G52: ValidationException | H52: Pass
A53: IN_SERVICE/cancel() | B53: UT08-TC024 | C53: IN_SERVICE | D53: cancel() | E53: − | F53: ValidationException "Cannot execute action 'cancel' from booking status IN_SERVICE" • สถานะคงเดิม | G53: ValidationException | H53: Pass
A54: IN_SERVICE/markNoShow() | B54: UT08-TC025 | C54: IN_SERVICE | D54: markNoShow() | E54: − | F54: ValidationException "Cannot execute action 'markNoShow' from booking status IN_SERVICE" • สถานะคงเดิม | G54: ValidationException | H54: Pass
A55: COMPLETED/confirm() | B55: UT08-TC026 | C55: COMPLETED | D55: confirm() | E55: − | F55: ValidationException "Cannot execute action 'confirm' from booking status COMPLETED" • สถานะคงเดิม | G55: ValidationException | H55: Pass
A56: COMPLETED/checkIn() | B56: UT08-TC027 | C56: COMPLETED | D56: checkIn() | E56: − | F56: ValidationException "Cannot execute action 'checkIn' from booking status COMPLETED" • สถานะคงเดิม | G56: ValidationException | H56: Pass
A57: COMPLETED/startService() | B57: UT08-TC028 | C57: COMPLETED | D57: startService() | E57: − | F57: ValidationException "Cannot execute action 'startService' from booking status COMPLETED" • สถานะคงเดิม | G57: ValidationException | H57: Pass
A58: COMPLETED/complete() | B58: UT08-TC029 | C58: COMPLETED | D58: complete() | E58: − | F58: ValidationException "Cannot execute action 'complete' from booking status COMPLETED" • สถานะคงเดิม | G58: ValidationException | H58: Pass
... A74: updateBookingStatus | B74: UT08-TC045 | C74: CONFIRMED เริ่มอีก 1 วัน | D74: updateBookingStatus(NO_SHOW) | E74: − | F74: ValidationException ยังไม่เลยเวลานัด 15 นาที | G74: nothing was thrown | H74: Pass

Sheet UT09_StateFactory_EC
A1: Equivalence Class Design
A2: Valid EC | E2: Invalid EC
A3: EC ID | B3: Condition | E3: EC ID | F3: Condition
A4: V1 | B4: status = PENDING | E4: − | F4: ไม่มี: ทุกค่าของ enum ใช้ได้
A5: V2 | B5: status = CONFIRMED
A6: V3 | B6: status = CHECKED_IN
A7: V4 | B7: status = IN_SERVICE
A8: V5 | B8: status = COMPLETED
A9: V6 | B9: status = CANCELLED
A10: V7 | B10: status = NO_SHOW
A11: V8 | B11: status = null (ค่าเริ่มต้นของ entity ใหม่)
A13: Test Case Design and Test Results
A15: Project Name: | B15: BookingStateFactory.getState(BookingStatus) | H15: Student ID: | I15: 673380049-4
A16: Test Strategy: | B16: Functional testing - Strong Normal Equivalence Class Testing (ทุกค่าใน enum) | H16: Designer: | I16: Piyachayanin
A17: Test Environtment: | B17: Lenovo LOQ 15AHP11, CPU AMD Ryzen 7 250, Memory 16 GB DDR5, GPU NVIDIA GeForce RTX 5050 Laptop, OS Window 11 | H17: Date: | I17: 09/10/2026
A18: Method under test: | B18: static BookingState getState(BookingStatus status)
A19: Requirement อ้างอิง: | B19: design-patterns.md (State) • SRS 7.1
A21: Test Case ID | B21: Input | C21: Expected Result | D21: Actual Result | E21: Status (Pass/Fail/No run)
B22: status
A23: UT09-TC001 | B23: PENDING | C23: (V1) คืน PendingState และ getStatus() = PENDING | D23: PENDING | E23: Pass
A24: UT09-TC002 | B24: CONFIRMED | C24: (V2) คืน ConfirmedState และ getStatus() = CONFIRMED | D24: CONFIRMED | E24: Pass
A25: UT09-TC003 | B25: CHECKED_IN | C25: (V3) คืน CheckedInState และ getStatus() = CHECKED_IN | D25: CHECKED_IN | E25: Pass
A26: UT09-TC004 | B26: IN_SERVICE | C26: (V4) คืน InServiceState และ getStatus() = IN_SERVICE | D26: IN_SERVICE | E26: Pass
A27: UT09-TC005 | B27: COMPLETED | C27: (V5) คืน CompletedState และ getStatus() = COMPLETED | D27: COMPLETED | E27: Pass
A28: UT09-TC006 | B28: CANCELLED | C28: (V6) คืน CancelledState และ getStatus() = CANCELLED | D28: CANCELLED | E28: Pass
A29: UT09-TC007 | B29: NO_SHOW | C29: (V7) คืน NoShowState และ getStatus() = NO_SHOW | D29: NO_SHOW | E29: Pass
A30: UT09-TC008 | B30: null | C30: (V8) คืน PendingState | D30: คืน PendingState | E30: Pass

Sheet UT10_Availability_BVA
A1: Test Case Design and Test Results | I1: durationMinutes
H2: min- | I2: 0
A3: Project Name: | B3: AvailabilityServiceImpl.checkAvailability – จำนวนรอบเวลาตามระยะเวลาบริการ | D3: Student ID: | E3: 673380049-4 | H3: min | I3: 1
A4: Test Strategy: | B4: Functional testing - Robustness Testing | D4: Designer: | E4: Piyachayanin | H4: min+ | I4: 2
A5: Test Environtment: | B5: Lenovo LOQ 15AHP11, CPU AMD Ryzen 7 250, Memory 16 GB DDR5, GPU NVIDIA GeForce RTX 5050 Laptop, OS Window 11 | D5: Date: | E5: 09/10/2026 | H5: nom | I5: 90
A6: Method under test: | B6: AvailabilityResponseDTO checkAvailability(LocalDate date, Long serviceId, Integer durationMinutes) | H6: max- | I6: 719
A7: Requirement อ้างอิง: | B7: UC-08 • BR-BKG-02 • SRS 7.2 | H7: max+ | I7: 721
A8: TC008 เป็นเคส robustness เพิ่มนอกตาราง BVA (ค่าที่ทำให้เวลาวนข้ามวัน)
A10: Test Case ID | B10: Input | C10: Expected Result | D10: Actual Result | E10: Status (Pass/Fail/No run)
B11: durationMinutes
A12: UT10-TC001 | B12: 0 | C12: ใช้ระยะเวลาจาก option แรก = 60 • durationMinutes ใน response = 60 • 12 รอบ (10:00–21:00) | E12: Pass
A13: UT10-TC002 | B13: 1 | C13: durationMinutes = 1 • 12 รอบ (10:00–21:00) รอบสุดท้ายจบ 21:01 | E13: Pass
A14: UT10-TC003 | B14: 2 | C14: 12 รอบ | D14: 12 รอบ | E14: Pass
A15: UT10-TC004 | B15: 90 | C15: 11 รอบ (10:00–20:00) • ไม่มีรอบ 21:00 เพราะจะจบ 22:30 | D15: 11 รอบ | E15: Pass
A16: UT10-TC005 | B16: 719 | C16: 1 รอบ (10:00–21:59) | D16: 1 รอบ | E16: Pass
A17: UT10-TC006 | B17: 720 | C17: 1 รอบ (10:00–22:00) | D17: 1 รอบ | E17: Pass
A18: UT10-TC007 | B18: 721 | C18: 0 รอบ (availableSlots ว่าง) ไม่เกิด Exception | D18: 0 รอบ | E18: Pass
A19: UT10-TC008 | B19: 900 (นอกโดเมน: เกินเที่ยงคืน) | C19: 0 รอบ | D19: 22 รอบ | E19: Pass

Sheet UT11_Availability_EC
A1: Equivalence Class Design
A2: Valid EC | E2: Invalid EC
A3: EC ID | B3: Condition | E3: EC ID | F3: Condition
A4: V1 | B4: date ระบุมา | E4: I1 | F4: serviceId ไม่มีอยู่
A5: V2 | B5: date = null → ใช้วันนี้ | E5: I2 | F5: service inactive
A6: V3 | B6: service มีอยู่และ active | E6: I3 | F6: วันนั้นร้านปิด (isClosed = true)
A7: V4 | B7: มี BusinessHours ของวันนั้นและเปิด
A8: V5 | B8: ไม่มี BusinessHours ของวันนั้น → ใช้ค่าเริ่มต้น 10:00–21:00
A9: V6 | B9: หมอนวดหยุดถูกตัดออกจาก availableTherapists
A10: V7 | B10: รอบที่ไม่มีห้องว่าง → available = false
A11: V8 | B11: booking เดิมสถานะ COMPLETED/CANCELLED/NO_SHOW ไม่ล็อกทรัพยากร
A13: Test Case Design and Test Results
A15: Project Name: | B15: AvailabilityServiceImpl.checkAvailability – สภาพร้านและทรัพยากร | H15: Student ID: | I15: 673380049-4
A16: Test Strategy: | B16: Functional testing - Weak Robust Equivalence Class Testing | H16: Designer: | I16: Piyachayanin
A17: Test Environtment: | B17: Lenovo LOQ 15AHP11, CPU AMD Ryzen 7 250, Memory 16 GB DDR5, GPU NVIDIA GeForce RTX 5050 Laptop, OS Window 11 | H17: Date: | I17: 09/10/2026
A18: Method under test: | B18: checkAvailability(date, serviceId, durationMinutes)
A19: Requirement อ้างอิง: | B19: UC-08, UC-08a, UC-08b • SRS 7.2
A21: Test Case ID | B21: Input | E21: Expected Result | F21: Actual Result | G21: Status (Pass/Fail/No run)
B22: date | C22: serviceId | D22: สภาพข้อมูล (mock)
A23: UT11-TC001 | B23: 2026-11-09 | C23: 1 | D23: ร้านเปิด 10–22, T5 + R101 ว่าง | E23: (V1,V3,V4) 12 รอบ ทุกรอบ available = true, availableTherapists มี T5, availableRooms มี R101 | F23: 12 รอบ ทุกรอบ available = true, availableTherapists มี T5, availableRooms มี R101 | G23: Pass
A24: UT11-TC002 | B24: null | C24: 1 | D24: ร้านเปิด | E24: (V2) date ใน response = วันนี้ | F24: date ใน response = วันนี้ | G24: Pass
A25: UT11-TC003 | B25: 2026-11-09 | C25: 1 | D25: ไม่มีแถว BusinessHours วันจันทร์ | E25: (V5) 11 รอบ (10:00–20:00) | F25: 11 รอบ | G25: Pass
A26: UT11-TC004 | B26: 2026-11-09 | C26: 1 | D26: T5 isDayOff, T8 ว่าง | E26: (V6) availableTherapists ทุกรอบมีแค่ T8 | F26: availableTherapists ทุกรอบมีแค่ T8 | G26: Pass
A27: UT11-TC005 | B27: 2026-11-09 | C27: 1 | D27: R101 มีคิว 13:00–14:00 (ห้องเดียว) | E27: (V7) รอบ 12:00, 13:00, 14:00 available = false (12:00 จบ 13:00 + buffer 15 ชนคิว, 14:00 ติด buffer ถึง 14:15) • รอบอื่น true | F27: รอบ 12:00, 13:00, 14:00 available = false (12:00 จบ 13:00 + buffer 15 ชนคิว, 14:00 ติด buffer ถึง 14:15) • รอบอื่น true | G27: Pass
A28: UT11-TC006 | B28: 2026-11-09 | C28: 1 | D28: R101 (ห้องเดียว) มีคิว 13:00–14:00 สถานะ COMPLETED | E28: (V8) รอบ 13:00 available = true เพราะ COMPLETED ไม่ล็อกทรัพยากร | F28: available = flase | G28: Pass
A29: UT11-TC007 | B29: 2026-11-09 | C29: 999 | D29: − | E29: (I1) NotFoundException | F29: NotFoundException | G29: Pass
A30: UT11-TC008 | B30: 2026-11-09 | C30: 3 | D30: S3 inactive | E30: (I2) ValidationException "Selected service is currently inactive" | F30: ValidationException | G30: Pass
A31: UT11-TC009 | B31: 2026-11-09 | C31: 1 | D31: BusinessHours MONDAY isClosed = true | E31: (I3) availableSlots ว่าง ไม่เกิด Exception | F31: availableSlots ว่าง | G31: Pass

Sheet UT12_BookingMapper_EC
A1: Equivalence Class Design
A2: Valid EC | E2: Invalid EC
A3: EC ID | B3: Condition | E3: EC ID | F3: Condition
A4: V1 | B4: Booking มีครบทุก relation | E4: − | F4: ไม่มี: ทุกกรณีต้องไม่โยน Exception
A5: V2 | B5: therapist = null
A6: V3 | B6: service, room, durationOption, customer = null
A7: V4 | B7: status = null
A8: V5 | B8: room มีแต่ roomType = null
A9: V6 | B9: booking = null
A10: V7 | B10: List = null หรือว่าง
A12: Test Case Design and Test Results
A14: Project Name: | B14: BookingMapper (toMyBookingResponse / toBookingResponse / list) | H14: Student ID: | I14: 673380049-4
A15: Test Strategy: | B15: Functional testing - Weak Normal Equivalence Class Testing | H15: Designer: | I15: Piyachayanin
A16: Test Environtment: | B16: Lenovo LOQ 15AHP11, CPU AMD Ryzen 7 250, Memory 16 GB DDR5, GPU NVIDIA GeForce RTX 5050 Laptop, OS Window 11 | H16: Date: | I16: 09/10/2026
A17: Method under test: | B17: toMyBookingResponse, toMyBookingResponses, toBookingResponse, toBookingResponses
A18: Requirement อ้างอิง: | B18: UC-09 • DTO Pattern + Mapper
A20: Test Case ID | B20: Input | D20: Expected Result | E20: Actual Result | F20: Status (Pass/Fail/No run)
B21: เมธอด | C21: Booking ที่ส่งเข้า
A22: UT12-TC001 | B22: toBookingResponse | C22: ครบทุก relation | D22: (V1) map ครบทุก field: customerId/Name/Phone, serviceId/Name, therapistId/Name, roomId/Number/Type, status, channel, notes | E22: map ครบทุก field | F22: Pass
A23: UT12-TC002 | B23: toMyBookingResponse | C23: ครบทุก relation | D23: (V1) serviceName, therapistName, roomNumber, durationMinutes = 60, status = "CONFIRMED" | E23: serviceName, therapistName, roomNumber, durationMinutes = 60, status = "CONFIRMED" | F23: Pass
A24: UT12-TC003 | B24: toBookingResponse | C24: therapist = null | D24: (V2) therapistId และ therapistName = null | E24: therapistId และ therapistName = null | F24: Pass
A25: UT12-TC004 | B25: toBookingResponse | C25: service/room/option/customer = null | D25: (V3) field ที่เกี่ยวข้องเป็น null | E25: field ที่เกี่ยวข้องเป็น null | F25: Pass
A26: UT12-TC005 | B26: toMyBookingResponse | C26: status = null | D26: (V4) status = null | E26: status = null | F26: Pass
A27: UT12-TC006 | B27: toBookingResponse | C27: room.roomType = null | D27: (V5) roomNumber มีค่า, roomType = null | E27: roomNumber มีค่า, roomType = null | F27: Pass
A28: UT12-TC007 | B28: toBookingResponse / toMyBookingResponse | C28: null | D28: (V6) คืน null | E28: null | F28: Pass
A29: UT12-TC008 | B29: toBookingResponses / toMyBookingResponses | C29: null และ [] | D29: (V7) คืน List ว่าง | E29: คืน List ว่าง | F29: Pass

Sheet UT13_ProcessPayment_DT
A1: Condition | B1: Rule#1 | C1: Rule#2 | D1: Rule#3 | E1: Rule#4 | F1: Rule#5 | G1: Rule#6 | H1: Rule#7 | I1: Rule#8
A2: C1: bookingId = null | B2: Y | C2: N | D2: N | E2: N | F2: N | G2: N | H2: N | I2: N
A3: C2: request หรือ paymentMethod = null | B3: − | C3: Y | D3: N | E3: N | F3: N | G3: N | H3: N | I3: N
A4: C3: พบ booking | B4: − | C4: − | D4: N | E4: Y | F4: Y | G4: Y | H4: Y | I4: Y
A5: C4: มี Payment สถานะ COMPLETED อยู่แล้ว | B5: − | C5: − | D5: − | E5: Y | F5: N | G5: N | H5: N | I5: N
A6: C5: totalPrice > 0 | B6: − | C6: − | D6: − | E6: − | F6: N | G6: Y | H6: Y | I6: Y
A7: C6: strategy.processPayment สำเร็จ | B7: − | C7: − | D7: − | E7: − | F7: − | G7: N | H7: Y | I7: Y
A8: C7: Payment เดิมสถานะ FAILED/PENDING | B8: − | C8: − | D8: − | E8: − | F8: − | G8: − | H8: N | I8: Y
A9: Action
A10: A1: ValidationException "Booking ID cannot be null" | B10: X
A11: A2: ValidationException "Payment method is required" | C11: X
A12: A3: NotFoundException | D12: X
A13: A4: ConflictException จ่ายซ้ำ | E13: X
A14: A5: ValidationException ราคาไม่ถูกต้อง | F14: X
A15: A6: save Payment FAILED + ValidationException | G15: X
A16: A7: save Payment COMPLETED + คืน DTO | H16: X | I16: X
A17: Impossible
A19: Test Case Design and Test Results
A21: Project Name: | B21: PaymentServiceImpl.processPayment – ตรวจเงื่อนไขและผลการชำระ | H21: Student ID: | I21: 673380049-4
A22: Test Strategy: | B22: Functional testing - Decision Table (Limited Entry) | H22: Designer: | I22: Piyachayanin
A23: Test Environtment: | B23: Lenovo LOQ 15AHP11, CPU AMD Ryzen 7 250, Memory 16 GB DDR5, GPU NVIDIA GeForce RTX 5050 Laptop, OS Window 11 | H23: Date: | I23: 09/10/2026
A24: Method under test: | B24: PaymentResponseDTO processPayment(Long bookingId, PaymentRequestDTO request)
A25: Requirement อ้างอิง: | B25: UC-19 • BR-PAY-01 Single Full Settlement • BR-PAY-02 Immutable Payment
A27: Rule# | B27: Test Case ID | C27: Input | F27: Expected Result | G27: Actual Result | H27: Status (Pass/Fail/No run)
C28: bookingId | D28: paymentMethod | E28: สภาพข้อมูล (mock)
A29: R1 | B29: UT13-TC001 | C29: null | D29: CASH | E29: − | F29: ValidationException "Booking ID cannot be null" • ไม่เรียก repository | G29: ValidationException | H29: Pass
A30: R2 | B30: UT13-TC002 | C30: 10 | D30: null | E30: − | F30: ValidationException "Payment method is required" | G30: ValidationException | H30: Pass
A31: R3 | B31: UT13-TC003 | C31: 999 | D31: CASH | E31: ไม่พบ booking | F31: NotFoundException | G31: NotFoundExceptionv | H31: Pass
A32: R4 | B32: UT13-TC004 | C32: 10 | D32: QR_PROMPTPAY | E32: มี Payment COMPLETED อยู่แล้ว | F32: ConflictException "...already been completed..." • ไม่เรียก strategy | G32: ConflictException | H32: Pass
A33: R5 | B33: UT13-TC005 | C33: 10 | D33: CASH | E33: totalPrice = 0.00 | F33: ValidationException "Invalid booking total price" | G33: ValidationException | H33: Pass
A34: R6 | B34: UT13-TC006 | C34: 10 | D34: CREDIT_CARD | E34: strategy คืน false | F34: save Payment ที่ status = FAILED 1 ครั้ง แล้วโยน ValidationException • สถานะ booking ไม่เปลี่ยน | G34: ValidationException สถานะ booking ไม่เปลี่ยน | H34: Pass
A35: R7 | B35: UT13-TC007 | C35: 10 | D35: CASH | E35: ไม่มี Payment เดิม | F35: Payment COMPLETED: gross = net = 600.00, discount = 0, paymentReferenceCode ขึ้นต้น PAY-, receiptNumber ขึ้นต้น REC- | G35: Payment COMPLETED | H35: Pass
A36: R8 | B36: UT13-TC008 | C36: 10 | D36: CASH | E36: มี Payment เดิมสถานะ FAILED | F36: ชำระได้ (ไม่ถือว่าจ่ายซ้ำ) • Payment ใหม่ COMPLETED | G36: Payment ใหม่ COMPLETED | H36: Pass

Sheet UT14_Payment_Promo_Status_EC
A1: Equivalence Class Design
A2: Valid EC | E2: Invalid EC
A3: EC ID | B3: Condition | E3: EC ID | F3: Condition
A4: V1 | B4: ไม่มี promoCode | E4: I1 | F4: รหัสไม่รู้จัก → ไม่ลด
A5: V2 | B5: FIWDEE20 (ลด 20%) | E5: I2 | F5: WELCOME100 แต่ราคา < 300 → ไม่ลด
A6: V3 | B6: WELCOME100 และราคา ≥ 300 | E6: I3 | F6: สถานะ CHECKED_IN (ห้ามข้ามไป COMPLETED)
A7: V4 | B7: รหัสพิมพ์เล็ก/มีช่องว่าง เช่น " fiwdee20 " | E7: I4 | F7: สถานะ CANCELLED / NO_SHOW (ห้ามรับเงิน)
A8: V5 | B8: สถานะ PENDING → CONFIRMED
A9: V6 | B9: สถานะ CONFIRMED → คงเดิม
A10: V7 | B10: สถานะ IN_SERVICE → COMPLETED
A12: Test Case Design and Test Results
A14: Project Name: | B14: PaymentServiceImpl.processPayment – ส่วนลดและสถานะ booking หลังชำระ | H14: Student ID: | I14: 673380049-4
A15: Test Strategy: | B15: Functional testing - Weak Robust Equivalence Class Testing | H15: Designer: | I15: Piyachayanin
A16: Test Environtment: | B16: Lenovo LOQ 15AHP11, CPU AMD Ryzen 7 250, Memory 16 GB DDR5, GPU NVIDIA GeForce RTX 5050 Laptop, OS Window 11 | H16: Date: | I16: 09/10/2026
A17: Method under test: | B17: processPayment(...) ขั้นที่ 4 (ส่วนลด) และ 8 (อัปเดตสถานะ booking)
A18: Requirement อ้างอิง: | B18: BR-PAY-01 • SRS 7.1 • BR-QUE-03 • UC-07 ข้อ 13
A20: Test Case ID | B20: Input | E20: Expected Result | F20: Actual Result | G20: Status (Pass/Fail/No run)
B21: สถานะ booking | C21: totalPrice | D21: promoCode
A22: UT14-TC001 | B22: CONFIRMED | C22: 600.00 | D22: null | E22: (V1,V6) discount 0, net 600.00 • สถานะคง CONFIRMED | F22: discount 0, net 600.00 • สถานะคง CONFIRMED | G22: Pass
A23: UT14-TC002 | B23: CONFIRMED | C23: 600.00 | D23: FIWDEE20 | E23: (V2) discount 120.00, net 480.00 | F23: discount 120.00, net 480.00 | G23: Pass
A24: UT14-TC003 | B24: CONFIRMED | C24: 600.00 | D24: WELCOME100 | E24: (V3) discount 100.00, net 500.00 | F24: discount 100.00, net 500.00 | G24: Pass
A25: UT14-TC004 | B25: CONFIRMED | C25: 600.00 | D25: " fiwdee20 " | E25: (V4) discount 120.00 | F25: discount 120.00 | G25: Pass
A26: UT14-TC005 | B26: CONFIRMED | C26: 600.00 | D26: SALE50 | E26: (I1) discount 0, net 600.00 ไม่โยน Exception | F26: discount 0, net 600.00 | G26: Pass
A27: UT14-TC006 | B27: CONFIRMED | C27: 250.00 | D27: WELCOME100 | E27: (I2) discount 0, net 250.00 | F27: discount 0, net 250.00 | G27: Pass
A28: UT14-TC007 | B28: PENDING | C28: 600.00 | D28: null | E28: (V5) booking → CONFIRMED และ publish BookingStatusChangedEvent | F28: booking → CONFIRMED และ publish BookingStatusChangedEvent | G28: Pass
A29: UT14-TC008 | B29: IN_SERVICE | C29: 600.00 | D29: null | E29: (V7) booking → COMPLETED และ publish event | F29: booking → COMPLETED และ publish event | G29: Pass
A30: UT14-TC009 | B30: CHECKED_IN | C30: 600.00 | D30: null | E30: (I3) ชำระได้ แต่สถานะต้องคง CHECKED_IN | F30: สถานะ COMPLETED | G30: Fail
A31: UT14-TC010 | B31: CANCELLED | C31: 600.00 | D31: null | E31: (I4) ValidationException ห้ามรับเงิน | F31: nothing was thrown | G31: Fail
A32: UT14-TC011 | B32: NO_SHOW | C32: 600.00 | D32: null | E32: (I4) ValidationException | F32: nothing was thrown | G32: Fail

Sheet UT15_FixedDiscount_BVA
A1: Test Case Design and Test Results | J1: totalPrice (isApplicable) | K1: grossAmount (calculateDiscount)
I2: min- | J2: 299.99 | K2: 0.00
A3: Project Name: | B3: FixedAmountDiscountStrategy (WELCOME100) | E3: Student ID: | F3: 673380049-4 | I3: min | J3: 300.00 | K3: 0.01
A4: Test Strategy: | B4: Functional testing - Robustness Testing | E4: Designer: | F4: Piyachayanin | I4: min+ | J4: 300.01 | K4: 0.02
A5: Test Environtment: | B5: Lenovo LOQ 15AHP11, CPU AMD Ryzen 7 250, Memory 16 GB DDR5, GPU NVIDIA GeForce RTX 5050 Laptop, OS Window 11 | E5: Date: | F5: 09/10/2026 | I5: nom | J5: 600.00 | K5: 50.00
A6: Method under test: | B6: isApplicable(Booking) : totalPrice ≥ 300.00 • calculateDiscount(gross) : min(gross, 100.00), gross ≤ 0 → 0 | I6: max- | J6: − | K6: 99.99
A7: Requirement อ้างอิง: | B7: Discount Strategy (design-patterns.md) • BR-PAY-01 | I7: max+ | J7: − | K7: 100.01
A9: Test Case ID | B9: Input | D9: Expected Result | E9: Actual Result | F9: Status (Pass/Fail/No run)
B10: เมธอด | C10: ค่าที่ส่ง
A11: UT15-TC001 | B11: isApplicable | C11: totalPrice 299.99 | D11: false | E11: false | F11: Pass
A12: UT15-TC002 | B12: isApplicable | C12: totalPrice 300.00 | D12: true | E12: true | F12: Pass
A13: UT15-TC003 | B13: isApplicable | C13: totalPrice 300.01 | D13: true | E13: true | F13: Pass
A14: UT15-TC004 | B14: isApplicable | C14: totalPrice 600.00 | D14: true | E14: true | F14: Pass
A15: UT15-TC005 | B15: isApplicable | C15: totalPrice null / booking null | D15: false | E15: false | F15: Pass
A16: UT15-TC006 | B16: calculateDiscount | C16: 0.00 | D16: 0 | E16: 0 | F16: Pass
A17: UT15-TC007 | B17: calculateDiscount | C17: 0.01 | D17: 0.01 | E17: 0.01 | F17: Pass
A18: UT15-TC008 | B18: calculateDiscount | C18: 0.02 | D18: 0.02 | E18: 0.02 | F18: Pass
A19: UT15-TC009 | B19: calculateDiscount | C19: 50.00 | D19: 50.00 | E19: 50.00 | F19: Pass
A20: UT15-TC010 | B20: calculateDiscount | C20: 99.99 | D20: 99.99 | E20: 99.99 | F20: Pass
A21: UT15-TC011 | B21: calculateDiscount | C21: 100.00 | D21: 100.00 | E21: 100.00 | F21: Pass
A22: UT15-TC012 | B22: calculateDiscount | C22: 100.01 | D22: 100.00 | E22: 100.00 | F22: Pass
... A24: UT15-TC014 | B24: getPromotionCode | C24: − | D24: "WELCOME100" | E24: "WELCOME100" | F24: Pass

Sheet UT16_PercentDiscount_EC
A1: Equivalence Class Design
A2: Valid EC | E2: Invalid EC
A3: EC ID | B3: Condition | E3: EC ID | F3: Condition
A4: V1 | B4: ผลคูณลงตัว 2 ตำแหน่ง | E4: I1 | F4: gross = 0
A5: V2 | B5: หลักที่ 3 < 5 → ปัดลง | E5: I2 | F5: gross ติดลบ
A6: V3 | B6: หลักที่ 3 = 5 → ปัดขึ้น (HALF_UP) | E6: I3 | F6: gross = null
A7: V4 | B7: booking ราคา > 0 → ใช้ได้ | E7: I4 | F7: booking ราคา 0 / null / booking null
A9: Test Case Design and Test Results
A11: Project Name: | B11: PercentageDiscountStrategy (FIWDEE20) | H11: Student ID: | I11: 673380049-4
A12: Test Strategy: | B12: Functional testing - Weak Robust Equivalence Class Testing | H12: Designer: | I12: Piyachayanin
A13: Test Environtment: | B13: Lenovo LOQ 15AHP11, CPU AMD Ryzen 7 250, Memory 16 GB DDR5, GPU NVIDIA GeForce RTX 5050 Laptop, OS Window 11 | H13: Date: | I13: 09/10/2026
A14: Method under test: | B14: isApplicable(Booking) : totalPrice > 0 • calculateDiscount(gross) = gross × 0.20 ปัดทศนิยม 2 ตำแหน่งแบบ HALF_UP
A15: Requirement อ้างอิง: | B15: Discount Strategy (design-patterns.md)
A17: Test Case ID | B17: Input | D17: Expected Result | E17: Actual Result | F17: Status (Pass/Fail/No run)
B18: เมธอด | C18: ค่าที่ส่ง
A19: UT16-TC001 | B19: calculateDiscount | C19: 600.00 | D19: (V1) 120.00 | E19: 120 | F19: Pass
A20: UT16-TC002 | B20: calculateDiscount | C20: 0.01 | D20: (V2) 0.00 (0.002) | E20: 0.00 (0.002) | F20: Pass
A21: UT16-TC003 | B21: calculateDiscount | C21: 0.03 | D21: (V3) 0.01 (0.006 ปัดขึ้น) | E21: 0.01 (0.006 ปัดขึ้น) | F21: Pass
A22: UT16-TC004 | B22: calculateDiscount | C22: 0.025 | D22: (V3) 0.01 (0.005 → HALF_UP) | E22: 0.01 (0.005 → HALF_UP) | F22: Pass
A23: UT16-TC005 | B23: isApplicable | C23: totalPrice 600.00 | D23: (V4) true | E23: TRUE | F23: Pass
A24: UT16-TC006 | B24: calculateDiscount | C24: 0.00 | D24: (I1) 0 | E24: 0 | F24: Pass
A25: UT16-TC007 | B25: calculateDiscount | C25: -10.00 | D25: (I2) 0 | E25: 0 | F25: Pass
A26: UT16-TC008 | B26: calculateDiscount | C26: null | D26: (I3) 0 | E26: 0 | F26: Pass
A27: UT16-TC009 | B27: isApplicable | C27: totalPrice 0.00 / null / booking null | D27: (I4) false | E27: FALSE | F27: Pass

Sheet UT17_DiscountFactory_EC
A1: Equivalence Class Design
A2: Valid EC | E2: Invalid EC
A3: EC ID | B3: Condition | E3: EC ID | F3: Condition
A4: V1 | B4: รหัสตรงตัว | E4: I1 | F4: รหัสไม่รู้จัก
A5: V2 | B5: รหัสต่างตัวพิมพ์ | E5: I2 | F5: null
A6: V3 | B6: รหัสมีช่องว่างหน้า/หลัง | E6: I3 | F6: "" หรือช่องว่างล้วน
A7: V4 | B7: รายการ strategy มีรหัสซ้ำ → ใช้ตัวแรก | E7: I4 | F7: factory สร้างด้วย list ว่าง/null
A9: Test Case Design and Test Results
A11: Project Name: | B11: DiscountStrategyFactory.findStrategy(promoCode) | H11: Student ID: | I11: 673380049-4
A12: Test Strategy: | B12: Functional testing - Weak Robust Equivalence Class Testing | H12: Designer: | I12: Piyachayanin
A13: Test Environtment: | B13: Lenovo LOQ 15AHP11, CPU AMD Ryzen 7 250, Memory 16 GB DDR5, GPU NVIDIA GeForce RTX 5050 Laptop, OS Window 11 | H13: Date: | I13: 09/10/2026
A14: Method under test: | B14: Optional<DiscountStrategy> findStrategy(String promoCode)
A15: Requirement อ้างอิง: | B15: Factory + Strategy (OCP)
A17: Test Case ID | B17: Input | D17: Expected Result | E17: Actual Result | F17: Status (Pass/Fail/No run)
B18: promoCode | C18: factory
A19: UT17-TC001 | B19: FIWDEE20 | C19: ปกติ | D19: (V1) Optional มี PercentageDiscountStrategy | E19: Optional มี PercentageDiscountStrategy | F19: Pass
A20: UT17-TC002 | B20: welcome100 | C20: ปกติ | D20: (V2) Optional มี FixedAmountDiscountStrategy | E20: Optional มี FixedAmountDiscountStrategy | F20: Pass
A21: UT17-TC003 | B21: " FIWDEE20 " | C21: ปกติ | D21: (V3) Optional มี PercentageDiscountStrategy | E21: Optional มี PercentageDiscountStrategy | F21: Pass
A22: UT17-TC004 | B22: DUP | C22: strategy A, B รหัส DUP ทั้งคู่ | D22: (V4) คืน A ไม่โยน IllegalStateException | E22: คืน A ไม่โยน IllegalStateException | F22: Pass
A23: UT17-TC005 | B23: SALE50 | C23: ปกติ | D23: (I1) Optional.empty() | E23: Optional.empty() | F23: Pass
A24: UT17-TC006 | B24: null | C24: ปกติ | D24: (I2) Optional.empty() | E24: Optional.empty() | F24: Pass
A25: UT17-TC007 | B25: " " | C25: ปกติ | D25: (I3) Optional.empty() | E25: Optional.empty() | F25: Pass
A26: UT17-TC008 | B26: FIWDEE20 | C26: new DiscountStrategyFactory(null) | D26: (I4) Optional.empty() | E26: Optional.empty() | F26: Pass

Sheet UT18_PaymentStrategy_EC
A1: Equivalence Class Design
A2: Valid EC | E2: Invalid EC
A3: EC ID | B3: Condition | E3: EC ID | F3: Condition
A4: V1 | B4: CASH | E4: I1 | F4: method = null
A5: V2 | B5: QR_PROMPTPAY | E5: I2 | F5: method ไม่มี strategy ลงทะเบียน
A6: V3 | B6: CREDIT_CARD | E6: I3 | F6: payment = null
A7: V4 | B7: Payment มี netAmount | E7: I4 | F7: netAmount = null
A8: V5 | B8: Payment มี paidAt อยู่แล้ว
A10: Test Case Design and Test Results
A12: Project Name: | B12: PaymentStrategyFactory + Cash/QR/CardPaymentStrategy | H12: Student ID: | I12: 673380049-4
A13: Test Strategy: | B13: Functional testing - Strong Normal Equivalence Class Testing (ทุกค่าใน PaymentMethod) | H13: Designer: | I13: Piyachayanin
A14: Test Environtment: | B14: Lenovo LOQ 15AHP11, CPU AMD Ryzen 7 250, Memory 16 GB DDR5, GPU NVIDIA GeForce RTX 5050 Laptop, OS Window 11 | H14: Date: | I14: 09/10/2026
A15: Method under test: | B15: PaymentStrategyFactory.getStrategy(method) • PaymentStrategy.processPayment(payment) • QRPaymentStrategy.generatePromptPayQR
A16: Requirement อ้างอิง: | B16: UC-19 • Strategy Pattern (ใบงานข้อ 5.2)
A18: Test Case ID | B18: Input | D18: Expected Result | E18: Actual Result | F18: Status (Pass/Fail/No run)
B19: เมธอด | C19: input
A20: UT18-TC001 | B20: getStrategy | C20: CASH | D20: (V1) CashPaymentStrategy | E20: CashPaymentStrategy | F20: Pass
A21: UT18-TC002 | B21: getStrategy | C21: QR_PROMPTPAY | D21: (V2) QRPaymentStrategy | E21: QRPaymentStrategy | F21: Pass
A22: UT18-TC003 | B22: getStrategy | C22: CREDIT_CARD | D22: (V3) CardPaymentStrategy | E22: CardPaymentStrategy | F22: Pass
A23: UT18-TC004 | B23: getStrategy | C23: null | D23: (I1) ValidationException "Payment method cannot be null" | E23: ValidationException "Payment method cannot be null" | F23: Pass
A24: UT18-TC005 | B24: getStrategy (factory มีแค่ Cash) | C24: CREDIT_CARD | D24: (I2) ValidationException "Unsupported payment method" | E24: ValidationException "Unsupported payment method" | F24: Pass
A25: UT18-TC006 | B25: Cash.processPayment | C25: net 480.00, paidAt null | D25: (V4) true, status COMPLETED, paidAt ไม่เป็น null | E25: true, status COMPLETED, paidAt ไม่เป็น null | F25: Pass
A26: UT18-TC007 | B26: Card.processPayment | C26: paidAt = 2026-11-02 10:00 | D26: (V5) true, paidAt คงค่าเดิม | E26: true, paidAt คงค่าเดิม | F26: Pass
A27: UT18-TC008 | B27: QR.processPayment | C27: null | D27: (I3) false | E27: FALSE | F27: Pass
A28: UT18-TC009 | B28: QR.processPayment | C28: netAmount null | D28: (I4) false, status ไม่เปลี่ยน | E28: false, status ไม่เปลี่ยน | F28: Pass
A29: UT18-TC010 | B29: QR.generatePromptPayQR | C29: net 480.00 | D29: (V4) "https://promptpay.io/0812345678/480.00" | E29: https://promptpay.io/0812345678/480.00 | F29: Pass

Sheet UT19_Refund_Amount_BVA
A1: Test Case Design and Test Results | I1: refundAmount
H2: min- | I2: 0.00
A3: Project Name: | B3: RefundServiceImpl.processRefund – จำนวนเงินคืน | D3: Student ID: | E3: 673380049-4 | H3: min | I3: 0.01
A4: Test Strategy: | B4: Functional testing - Robustness Testing | D4: Designer: | E4: Piyachayanin | H4: min+ | I4: 0.02
A5: Test Environtment: | B5: Lenovo LOQ 15AHP11, CPU AMD Ryzen 7 250, Memory 16 GB DDR5, GPU NVIDIA GeForce RTX 5050 Laptop, OS Window 11 | D5: Date: | E5: 09/10/2026 | H5: nom | I5: 300.00
A6: Method under test: | B6: RefundResponseDTO processRefund(RefundRequestDTO request) : 0 < refundAmount ≤ net − คืนไปแล้ว | H6: max- | I6: 599.99
A7: Requirement อ้างอิง: | B7: UC-10 A1 • BR-PAY-02 (Refund เป็น record แยก) | H7: max+ | I7: 600.01
A9: Test Case ID | B9: Input | C9: Expected Result | D9: Actual Result | E9: Status (Pass/Fail/No run)
B10: refundAmount
A11: UT19-TC001 | B11: 0.00 | C11: ValidationException "Refund amount must be greater than zero" | D11: ValidationException | E11: Pass
A12: UT19-TC002 | B12: 0.01 | C12: บันทึก Refund COMPLETED 0.01 • Payment คง COMPLETED | D12: บันทึก Refund COMPLETED 0.01 Payment คง COMPLETED | E12: Pass
A13: UT19-TC003 | B13: 0.02 | C13: บันทึก Refund • Payment คง COMPLETED | D13: บันทึก Refund Payment คง COMPLETED | E13: Pass
A14: UT19-TC004 | B14: 300.00 | C14: บันทึก Refund • Payment คง COMPLETED | D14: บันทึก Refund Payment คง COMPLETED | E14: Pass
A15: UT19-TC005 | B15: 599.99 | C15: บันทึก Refund • Payment คง COMPLETED | D15: บันทึก Refund Payment คง COMPLETED | E15: Pass
A16: UT19-TC006 | B16: 600.00 | C16: บันทึก Refund • Payment เปลี่ยนเป็น REFUNDED และถูก save | D16: บันทึก Refund Payment เปลี่ยนเป็น REFUNDED และถูก save | E16: Pass
A17: UT19-TC007 | B17: 600.01 | C17: ValidationException "...exceeds maximum remaining refundable balance (600.00)" | D17: ValidationException | E17: Pass

Sheet UT20_Refund_EC
A1: Equivalence Class Design
A2: Valid EC | E2: Invalid EC
A3: EC ID | B3: Condition | E3: EC ID | F3: Condition
A4: V1 | B4: Payment COMPLETED เคยคืนแล้ว 200 (COMPLETED) → คงเหลือ 400 | E4: I1 | F4: request = null หรือ paymentId = null
A5: V2 | B5: Refund เก่าสถานะ FAILED ไม่นับ | E5: I2 | F5: ไม่พบ Payment
A6: V3 | B6: processedByStaff ว่าง → "Staff" | E6: I3 | F6: Payment PENDING / FAILED
A7: V4 | B7: ดึง refund ล่าสุดของ payment ที่มี refund | E7: I4 | F7: คืนเกินยอดคงเหลือหลังคืนบางส่วน
E8: I5 | F8: getRefundByPaymentId ไม่มี refund
E9: I6 | F9: id = null ในเมธอด get
A11: Test Case Design and Test Results
A13: Project Name: | B13: RefundServiceImpl – เงื่อนไขอื่นของการคืนเงิน | H13: Student ID: | I13: 673380049-4
A14: Test Strategy: | B14: Functional testing - Weak Robust Equivalence Class Testing | H14: Designer: | I14: Piyachayanin
A15: Test Environtment: | B15: Lenovo LOQ 15AHP11, CPU AMD Ryzen 7 250, Memory 16 GB DDR5, GPU NVIDIA GeForce RTX 5050 Laptop, OS Window 11 | H15: Date: | I15: 09/10/2026
A16: Method under test: | B16: processRefund(...), getRefundByPaymentId(...), getRefundsByBookingId(...)
A17: Requirement อ้างอิง: | B17: UC-10 A1 • BR-PAY-02
A19: Test Case ID | B19: Input | D19: Expected Result | E19: Actual Result | F19: Status (Pass/Fail/No run)
B20: สภาพ Payment / refund เดิม | C20: request
A21: UT20-TC001 | B21: COMPLETED, คืนแล้ว 200 (COMPLETED) | C21: refund 400.00 | D21: (V1) สำเร็จ • Payment → REFUNDED | E21: สำเร็จ • Payment → REFUNDED | F21: Pass
A22: UT20-TC002 | B22: COMPLETED, refund เก่า 200 สถานะ FAILED | C22: refund 600.00 | D22: (V2) สำเร็จ (คงเหลือ 600) • Payment → REFUNDED | E22: สำเร็จ (คงเหลือ 600) • Payment → REFUNDED | F22: Pass
A23: UT20-TC003 | B23: COMPLETED | C23: refund 100, processedByStaff = " " | D23: (V3) processedByStaff = "Staff" | E23: processedByStaff = "Staff" | F23: Pass
A24: UT20-TC004 | B24: มี refund 2 รายการ | C24: getRefundByPaymentId(1) | D24: (V4) คืนรายการ id ล่าสุด | E24: คืนรายการ id ล่าสุด | F24: Pass
A25: UT20-TC005 | B25: − | C25: request = null | D25: (I1) ValidationException "Payment ID is required..." | E25: ValidationException | F25: Pass
A26: UT20-TC006 | B26: ไม่พบ Payment#999 | C26: paymentId 999, 100.00 | D26: (I2) NotFoundException | E26: NotFoundException | F26: Pass
A27: UT20-TC007 | B27: PENDING | C27: refund 100.00 | D27: (I3) ConflictException "...not COMPLETED..." | E27: ConflictException | F27: Pass
A28: UT20-TC008 | B28: COMPLETED, คืนแล้ว 200 | C28: refund 400.01 | D28: (I4) ValidationException เกินยอดคงเหลือ 400.00 | E28: ValidationException | F28: Pass
A29: UT20-TC009 | B29: ไม่มี refund | C29: getRefundByPaymentId(1) | D29: (I5) NotFoundException | E29: NotFoundException | F29: Pass
A30: UT20-TC010 | B30: − | C30: getRefundsByBookingId(null) | D30: (I6) ValidationException | E30: ValidationException | F30: Pass

Sheet UT21_CheckIn_Window_BVA
A1: Test Case Design and Test Results | J1: นาทีก่อนเวลานัด
I2: นอกโดเมน | J2: วันก่อนหน้า
A3: Project Name: | B3: QueueServiceImpl.checkInBooking – ช่วงเวลาที่ check-in ได้ | E3: Student ID: | F3: 673380049-4 | I3: ขอบ-1 | J3: 31
A4: Test Strategy: | B4: Functional testing - Robustness Testing (ขอบด้านเดียว) | E4: Designer: | F4: Piyachayanin | I4: ขอบ | J4: 30
A5: Test Environtment: | B5: Lenovo LOQ 15AHP11, CPU AMD Ryzen 7 250, Memory 16 GB DDR5, GPU NVIDIA GeForce RTX 5050 Laptop, OS Window 11 | E5: Date: | F5: 09/10/2026 | I5: ขอบ+1 | J5: 29
A6: Method under test: | B6: checkInBooking(bookingId) → validateCheckInTime: วันเดียวกัน และ now ≥ start − 30 นาที | I6: nom | J6: 10
A7: Requirement อ้างอิง: | B7: BR-QUE-01 • UC-12 A1
A9: Test Case ID | B9: Input | D9: Expected Result | E9: Actual Result | F9: Status (Pass/Fail/No run)
B10: now | C10: นาทีก่อนเวลานัด
A11: UT21-TC001 | B11: 2026-11-02 13:50 | C11: 10 | D11: สำเร็จ: booking → CHECKED_IN, publish event 1 ครั้ง, คืน QueueItem | E11: สำเร็จ | F11: Pass
A12: UT21-TC002 | B12: 2026-11-02 13:29 | C12: 31 | D12: ValidationException "...within 30 minutes..." • สถานะคง CONFIRMED | E12: ValidationException | F12: Pass
A13: UT21-TC003 | B13: 2026-11-02 13:30 | C13: 30 | D13: สำเร็จ | E13: สำเร็จ | F13: Pass
A14: UT21-TC004 | B14: 2026-11-02 13:31 | C14: 29 | D14: สำเร็จ | E14: สำเร็จ | F14: Pass
A15: UT21-TC005 | B15: 2026-11-01 13:50 | C15: วันก่อนหน้า | D15: ValidationException "...on its scheduled date" | E15: ValidationException | F15: Pass
A16: UT21-TC006 | B16: 2026-11-02 15:00 | C16: -60 (มาสาย) | D16: สำเร็จ (โค้ดไม่มีขอบบน — ดู Q4 กรณีสายเกิน 15 นาที) | E16: สำเร็จ | F16: Pass

Sheet UT22_CheckIn_Queue_EC
A1: Equivalence Class Design
A2: Valid EC | E2: Invalid EC
A3: EC ID | B3: Condition | E3: EC ID | F3: Condition
A4: V1 | B4: booking CONFIRMED | E4: I1 | F4: ไม่พบ booking
A5: V2 | B5: booking CHECKED_IN และมีคิวแล้ว (เรียกซ้ำ) | E5: I2 | F5: สถานะอื่น (PENDING, CANCELLED, ...)
A6: V3 | B6: booking CHECKED_IN แต่ยังไม่มีคิว | E6: I3 | F6: generateQueueItem กับ booking ที่ยังไม่ CHECKED_IN
A7: V4 | B7: วันนั้นยังไม่มีคิว → Q001 | E7: I4 | F7: callNextQueue ไม่มีคิว WAITING
A8: V5 | B8: มี Q001–Q003 → Q004
A9: V6 | B9: มีคิวที่เลขผิดรูปแบบ (null, "QX") → นับเป็น 0
A11: Test Case Design and Test Results
A13: Project Name: | B13: QueueServiceImpl – สถานะ booking ตอน check-in และเลขคิว | H13: Student ID: | I13: 673380049-4
A14: Test Strategy: | B14: Functional testing - Weak Robust Equivalence Class Testing | H14: Designer: | I14: Piyachayanin
A15: Test Environtment: | B15: Lenovo LOQ 15AHP11, CPU AMD Ryzen 7 250, Memory 16 GB DDR5, GPU NVIDIA GeForce RTX 5050 Laptop, OS Window 11 | H15: Date: | I15: 09/10/2026
A16: Method under test: | B16: checkInBooking(bookingId), generateQueueItem(Booking), callNextQueue()
A17: Requirement อ้างอิง: | B17: UC-12 • UC-13 • Observer (QueueListener)
A19: Test Case ID | B19: Input | D19: Expected Result | E19: Actual Result | F19: Status (Pass/Fail/No run)
B20: เมธอด | C20: สภาพข้อมูล
A21: UT22-TC001 | B21: checkInBooking(10) | C21: CONFIRMED, ไม่มีคิว | D21: (V1) CHECKED_IN, save booking, publish event (CONFIRMED→CHECKED_IN) | E21: CHECKED_IN, save booking, publish event | F21: Pass
A22: UT22-TC002 | B22: checkInBooking(10) | C22: CHECKED_IN, มีคิว Q002 | D22: (V2) คืน Q002 เดิม ไม่สร้างใหม่ ไม่ publish event | E22: คืน Q002 เดิม ไม่สร้างใหม่ ไม่ publish event | F22: Pass
A23: UT22-TC003 | B23: checkInBooking(10) | C23: CHECKED_IN, ไม่มีคิว | D23: (V3) สร้างคิวใหม่ status WAITING, priority 0 | E23: สร้างคิวใหม่ status WAITING, priority 0 | F23: Pass
A24: UT22-TC004 | B24: generateQueueItem(booking) | C24: วันนั้นไม่มีคิว | D24: (V4) queueNumber = "Q001" | E24: queueNumber = "Q001" | F24: Pass
A25: UT22-TC005 | B25: generateQueueItem(booking) | C25: มี Q001, Q002, Q003 | D25: (V5) queueNumber = "Q004" | E25: queueNumber = "Q004" | F25: Pass
A26: UT22-TC006 | B26: generateQueueItem(booking) | C26: มี Q001 และคิว queueNumber = null, "QX" | D26: (V6) queueNumber = "Q002" | E26: queueNumber = "Q002" | F26: Pass
A27: UT22-TC007 | B27: checkInBooking(999) | C27: ไม่พบ | D27: (I1) NotFoundException | E27: NotFoundException | F27: Pass
A28: UT22-TC008 | B28: checkInBooking(10) | C28: PENDING | D28: (I2) ValidationException "Only confirmed bookings can be checked in" | E28: ValidationException | F28: Pass
A29: UT22-TC009 | B29: generateQueueItem(booking) | C29: booking CONFIRMED | D29: (I3) ValidationException "...only be created after check-in" | E29: ValidationException | F29: Pass
A30: UT22-TC010 | B30: callNextQueue() | C30: ไม่มีคิว WAITING วันนี้ | D30: (I4) NotFoundException | E30: NotFoundException | F30: Pass

Sheet UT23_QueueStatus_DT
A1: Equivalence class
A2: EC1 (สถานะปัจจุบัน) = { WAITING, CALLED, IN_SERVICE, COMPLETED, CANCELLED }
A3: EC2 (สถานะที่ขอ) = { WAITING, CALLED, IN_SERVICE, COMPLETED, CANCELLED, null }
A5: Condition | B5: Rule#1 | C5: Rule#2 | D5: Rule#3 | E5: Rule#4 | F5: Rule#5
A6: C1: สถานะปัจจุบัน | B6: WAITING | C6: CALLED | D6: IN_SERVICE | E6: COMPLETED | F6: CANCELLED
A7: C2 = WAITING | B7: = | C7: ✗ | D7: ✗ | E7: ✗ | F7: ✗
A8: C2 = CALLED | B8: ✓ | C8: = | D8: ✗ | E8: ✗ | F8: ✗
A9: C2 = IN_SERVICE | B9: ✗ | C9: ✓ | D9: = | E9: ✗ | F9: ✗
A10: C2 = COMPLETED | B10: ✗ | C10: ✗ | D10: ✓ | E10: = | F10: ✗
A11: C2 = CANCELLED | B11: ✓ | C11: ✓ | D11: ✗ | E11: ✗ | F11: =
A12: Action
A13: A1: ✓ เปลี่ยนสถานะ + save | B13: X | C13: X | D13: X | E13: X | F13: X
A14: A2: = คืนคิวเดิมไม่ save | B14: X | C14: X | D14: X | E14: X | F14: X
A15: A3: ✗ ValidationException | B15: X | C15: X | D15: X | E15: X | F15: X
A16: Impossible
A18: Test Case Design and Test Results
A20: Project Name: | B20: QueueServiceImpl.updateQueueStatus – การเปลี่ยนสถานะคิว | F20: Student ID: | G20: 673380049-4
A21: Test Strategy: | B21: Functional testing - Decision Table (Extended Entry) แบบ State Transition Table | F21: Designer: | G21: Piyachayanin
A22: Test Environtment: | B22: Lenovo LOQ 15AHP11, CPU AMD Ryzen 7 250, Memory 16 GB DDR5, GPU NVIDIA GeForce RTX 5050 Laptop, OS Window 11 | F22: Date: | G22: 09/10/2026
A23: Method under test: | B23: QueueItem updateQueueStatus(Long queueId, QueueStatus status) → isAllowedTransition(current, requested)
A24: Requirement อ้างอิง: | B24: UC-13 • UC-16 • UC-17
A26: Rule# | B26: Test Case ID | C26: Input | E26: Expected Result | F26: Actual Result | G26: Status (Pass/Fail/No run)
C27: สถานะปัจจุบัน | D27: สถานะที่ขอ
A28: WAITING→WAITING | B28: UT23-TC001 | C28: WAITING | D28: WAITING | E28: คืนคิวเดิม ไม่เรียก save (สถานะเดียวกัน) | F28: คืนคิวเดิม ไม่เรียก save | G28: Pass
A29: WAITING→CALLED | B29: UT23-TC002 | C29: WAITING | D29: CALLED | E29: queueStatus = CALLED และตั้ง calledTime • save 1 ครั้ง | F29: queueStatus = CALLED | G29: Pass
A30: WAITING→IN_SERVICE | B30: UT23-TC003 | C30: WAITING | D30: IN_SERVICE | E30: ValidationException "Queue status cannot transition from WAITING to IN_SERVICE" | F30: ValidationException | G30: Pass
A31: WAITING→COMPLETED | B31: UT23-TC004 | C31: WAITING | D31: COMPLETED | E31: ValidationException "Queue status cannot transition from WAITING to COMPLETED" | F31: ValidationException | G31: Pass
A32: WAITING→CANCELLED | B32: UT23-TC005 | C32: WAITING | D32: CANCELLED | E32: queueStatus = CANCELLED • save 1 ครั้ง | F32: queueStatus = CANCELLED | G32: Pass
A33: CALLED→WAITING | B33: UT23-TC006 | C33: CALLED | D33: WAITING | E33: ValidationException "Queue status cannot transition from CALLED to WAITING" | F33: ValidationException | G33: Pass
A34: CALLED→CALLED | B34: UT23-TC007 | C34: CALLED | D34: CALLED | E34: คืนคิวเดิม ไม่เรียก save (สถานะเดียวกัน) | F34: คืนคิวเดิม ไม่เรียก save | G34: Pass
A35: CALLED→IN_SERVICE | B35: UT23-TC008 | C35: CALLED | D35: IN_SERVICE | E35: queueStatus = IN_SERVICE • save 1 ครั้ง | F35: queueStatus = CANCELLED | G35: Pass
A36: CALLED→COMPLETED | B36: UT23-TC009 | C36: CALLED | D36: COMPLETED | E36: ValidationException "Queue status cannot transition from CALLED to COMPLETED" | F36: ValidationException | G36: Pass
A37: CALLED→CANCELLED | B37: UT23-TC010 | C37: CALLED | D37: CANCELLED | E37: queueStatus = CANCELLED • save 1 ครั้ง | F37: queueStatus = CANCELLED | G37: Pass
A38: IN_SERVICE→WAITING | B38: UT23-TC011 | C38: IN_SERVICE | D38: WAITING | E38: ValidationException "Queue status cannot transition from IN_SERVICE to WAITING" | F38: ValidationException | G38: Pass
A39: IN_SERVICE→CALLED | B39: UT23-TC012 | C39: IN_SERVICE | D39: CALLED | E39: ValidationException "Queue status cannot transition from IN_SERVICE to CALLED" | F39: ValidationException | G39: Pass
... A53: null | B53: UT23-TC026 | C53: WAITING | D53: null | E53: ValidationException "Queue status is required" | F53: ValidationException | G53: Pass

Sheet UT24_TherapistExec_DT
A1: Equivalence class
A2: EC1 (action) = { START, COMPLETE }
A3: EC2 (therapistId) = { ตรงกับ booking, ไม่ตรง/null }
A5: Condition | B5: Rule#1 | C5: Rule#2 | D5: Rule#3 | E5: Rule#4 | F5: Rule#5 | G5: Rule#6 | H5: Rule#7
A6: C1: action | B6: START | C6: START | D6: START | E6: START | F6: COMPLETE | G6: COMPLETE | H6: COMPLETE
A7: C2: therapistId ตรงกับ booking | B7: N | C7: Y | D7: Y | E7: Y | F7: N | G7: Y | H7: Y
A8: C3: สถานะ booking | B8: − | C8: ≠ CHECKED_IN | D8: CHECKED_IN | E8: CHECKED_IN | F8: − | G8: ≠ IN_SERVICE หรือคิว ≠ IN_SERVICE | H8: IN_SERVICE
A9: C4: สถานะคิว | B9: − | C9: − | D9: ≠ CALLED | E9: CALLED | F9: − | G9: − | H9: IN_SERVICE
A10: Action
A11: A1: ValidationException ไม่ใช่หมอนวดที่รับคิว | B11: X | F11: X
A12: A2: ValidationException สถานะไม่ถูกต้อง | C12: X | D12: X | G12: X
A13: A3: booking IN_SERVICE, actualStartTime, ห้อง OCCUPIED, คิว IN_SERVICE, publish event | E13: X
A14: A4: booking COMPLETED, actualEndTime, ห้อง CLEANING, คิว COMPLETED, publish event | H14: X
A15: Impossible
A17: Test Case Design and Test Results
A19: Project Name: | B19: TherapistExecutionServiceImpl – เริ่ม/จบการให้บริการ | G19: Student ID: | H19: 673380049-4
A20: Test Strategy: | B20: Functional testing - Decision Table (Extended Entry) | G20: Designer: | H20: Piyachayanin
A21: Test Environtment: | B21: Lenovo LOQ 15AHP11, CPU AMD Ryzen 7 250, Memory 16 GB DDR5, GPU NVIDIA GeForce RTX 5050 Laptop, OS Window 11 | G21: Date: | H21: 09/10/2026
A22: Method under test: | B22: startService(queueId, therapistId) • completeService(queueId, therapistId)
A23: Requirement อ้างอิง: | B23: UC-16 • UC-17 • SRS 5.2 (ห้อง OCCUPIED / CLEANING) • Observer
A25: Rule# | B25: Test Case ID | C25: Input | F25: Expected Result | G25: Actual Result | H25: Status (Pass/Fail/No run)
C26: action | D26: therapistId | E26: booking / คิว
A27: R1 | B27: UT24-TC001 | C27: START | D27: 8 | E27: CHECKED_IN / CALLED | F27: ValidationException "...not assigned to the specified therapist" | G27: ValidationException | H27: Pass
A28: R1 | B28: UT24-TC002 | C28: START | D28: null | E28: CHECKED_IN / CALLED | F28: ValidationException (therapistId null) | G28: ValidationException | H28: Pass
A29: R2 | B29: UT24-TC003 | C29: START | D29: 5 | E29: CONFIRMED / CALLED | F29: ValidationException "Only checked-in bookings can start service" | G29: ValidationException | H29: Pass
A30: R3 | B30: UT24-TC004 | C30: START | D30: 5 | E30: CHECKED_IN / WAITING | F30: ValidationException "The customer must be called..." | G30: ValidationException | H30: Pass
A31: R4 | B31: UT24-TC005 | C31: START | D31: 5 | E31: CHECKED_IN / CALLED | F31: booking IN_SERVICE, actualStartTime ไม่ null, R101 OCCUPIED, updateQueueStatus(IN_SERVICE), event CHECKED_IN→IN_SERVICE | G31: booking IN_SERVICE, actualStartTime ไม่ null, R101 OCCUPIED, updateQueueStatus(IN_SERVICE), event CHECKED_IN→IN_SERVICE | H31: Pass
A32: R5 | B32: UT24-TC006 | C32: COMPLETE | D32: 8 | E32: IN_SERVICE / IN_SERVICE | F32: ValidationException ไม่ใช่หมอนวดที่รับคิว | G32: ValidationException | H32: Pass
A33: R6 | B33: UT24-TC007 | C33: COMPLETE | D33: 5 | E33: IN_SERVICE / CALLED | F33: ValidationException "Only an in-service queue item can be completed" | G33: ValidationException | H33: Pass
A34: R7 | B34: UT24-TC008 | C34: COMPLETE | D34: 5 | E34: IN_SERVICE / IN_SERVICE | F34: booking COMPLETED, actualEndTime ไม่ null, R101 CLEANING, updateQueueStatus(COMPLETED), event IN_SERVICE→COMPLETED | G34: booking COMPLETED, actualEndTime ไม่ null, R101 CLEANING, updateQueueStatus(COMPLETED), event IN_SERVICE→COMPLETED | H34: Pass

Sheet UT25_Review_Rating_BVA
A1: Test Case Design and Test Results | K1: overallRating | L1: therapistRating | M1: cleanlinessRating
J2: min- | K2: 0 | L2: 0 | M2: 0
A3: Project Name: | B3: ReviewServiceImpl.submitReview – คะแนน 3 ด้าน | F3: Student ID: | G3: 673380049-4 | J3: min | K3: 1 | L3: 1 | M3: 1
A4: Test Strategy: | B4: Functional testing - Robustness Testing | F4: Designer: | G4: Piyachayanin | J4: min+ | K4: 2 | L4: 2 | M4: 2
A5: Test Environtment: | B5: Lenovo LOQ 15AHP11, CPU AMD Ryzen 7 250, Memory 16 GB DDR5, GPU NVIDIA GeForce RTX 5050 Laptop, OS Window 11 | F5: Date: | G5: 09/10/2026 | J5: nom | K5: 3 | L5: 3 | M5: 3
A6: Method under test: | B6: Review submitReview(bookingId, overallRating, therapistRating, cleanlinessRating, comment) | J6: max- | K6: 4 | L6: 4 | M6: 4
A7: Requirement อ้างอิง: | B7: SRS 3.4 (ให้คะแนน 1–5 ดาว) • UC-18 | J7: max+ | K7: 6 | L7: 6 | M7: 6
A9: Test Case ID | B9: Input | E9: Expected Result | F9: Actual Result | G9: Status (Pass/Fail/No run)
B10: overallRating | C10: therapistRating | D10: cleanlinessRating
A11: UT25-TC001 | B11: 3 | C11: 3 | D11: 3 | E11: บันทึกรีวิวสำเร็จ (nom) | F11: บันทึกรีวิวสำเร็จ | G11: Pass
A12: UT25-TC002 | B12: 0 | C12: 3 | D12: 3 | E12: ValidationException "Overall rating must be between 1 and 5" • ไม่บันทึก | F12: ValidationException | G12: Pass
A13: UT25-TC003 | B13: 1 | C13: 3 | D13: 3 | E13: บันทึกรีวิวสำเร็จ (saveAndFlush 1 ครั้ง) | F13: บันทึกรีวิวสำเร็จ | G13: Pass
A14: UT25-TC004 | B14: 2 | C14: 3 | D14: 3 | E14: บันทึกรีวิวสำเร็จ (saveAndFlush 1 ครั้ง) | F14: บันทึกรีวิวสำเร็จ | G14: Pass
A15: UT25-TC005 | B15: 4 | C15: 3 | D15: 3 | E15: บันทึกรีวิวสำเร็จ (saveAndFlush 1 ครั้ง) | F15: บันทึกรีวิวสำเร็จ | G15: Pass
A16: UT25-TC006 | B16: 5 | C16: 3 | D16: 3 | E16: บันทึกรีวิวสำเร็จ (saveAndFlush 1 ครั้ง) | F16: บันทึกรีวิวสำเร็จ | G16: Pass
A17: UT25-TC007 | B17: 6 | C17: 3 | D17: 3 | E17: ValidationException "Overall rating must be between 1 and 5" • ไม่บันทึก | F17: ValidationException | G17: Pass
A18: UT25-TC008 | B18: 3 | C18: 0 | D18: 3 | E18: ValidationException "Therapist rating must be between 1 and 5" • ไม่บันทึก | F18: ValidationException | G18: Pass
A19: UT25-TC009 | B19: 3 | C19: 1 | D19: 3 | E19: บันทึกรีวิวสำเร็จ (saveAndFlush 1 ครั้ง) | F19: บันทึกรีวิวสำเร็จ | G19: Pass
A20: UT25-TC010 | B20: 3 | C20: 2 | D20: 3 | E20: บันทึกรีวิวสำเร็จ (saveAndFlush 1 ครั้ง) | F20: บันทึกรีวิวสำเร็จ | G20: Pass
A21: UT25-TC011 | B21: 3 | C21: 4 | D21: 3 | E21: บันทึกรีวิวสำเร็จ (saveAndFlush 1 ครั้ง) | F21: บันทึกรีวิวสำเร็จ | G21: Pass
A22: UT25-TC012 | B22: 3 | C22: 5 | D22: 3 | E22: บันทึกรีวิวสำเร็จ (saveAndFlush 1 ครั้ง) | F22: บันทึกรีวิวสำเร็จ | G22: Pass
... A29: UT25-TC019 | B29: 3 | C29: 3 | D29: 6 | E29: ValidationException "Cleanliness rating must be between 1 and 5" • ไม่บันทึก | F29: ValidationException | G29: Pass

Sheet UT26_Review_EC
A1: Equivalence Class Design
A2: Valid EC | E2: Invalid EC
A3: EC ID | B3: Condition | E3: EC ID | F3: Condition
A4: V1 | B4: booking COMPLETED ยังไม่มีรีวิว | E4: I1 | F4: ไม่พบ booking
A5: V2 | B5: comment มีช่องว่างหน้า/หลัง → trim | E5: I2 | F5: booking ยังไม่ COMPLETED
A6: V3 | B6: comment ว่างหรือช่องว่างล้วน → null | E6: I3 | F6: รีวิวซ้ำ
A7: V4 | B7: หมอนวดมีรีวิว 5, 4, 4 → average 4.33 | E7: I4 | F7: คะแนน = null
A8: V5 | B8: booking ไม่มีหมอนวด → ไม่คำนวณ average และไม่ error | E8: I5 | F8: ผู้รีวิวไม่ใช่เจ้าของ booking
A10: Test Case Design and Test Results
A12: Project Name: | B12: ReviewServiceImpl.submitReview – เงื่อนไขอื่น | H12: Student ID: | I12: 673380049-4
A13: Test Strategy: | B13: Functional testing - Weak Robust Equivalence Class Testing | H13: Designer: | I13: Piyachayanin
A14: Test Environtment: | B14: Lenovo LOQ 15AHP11, CPU AMD Ryzen 7 250, Memory 16 GB DDR5, GPU NVIDIA GeForce RTX 5050 Laptop, OS Window 11 | H14: Date: | I14: 09/10/2026
A15: Method under test: | B15: submitReview(...) • refreshTherapistAverageRating • normalizeComment
A16: Requirement อ้างอิง: | B16: UC-18 • SRS 3.4 • BR-SEC-01
A18: Test Case ID | B18: Input | D18: Expected Result | E18: Actual Result | F18: Status (Pass/Fail/No run)
B19: bookingId / สถานะ | C19: comment / อื่น ๆ
A20: UT26-TC001 | B20: 10 / COMPLETED | C20: "นวดดีมาก" | D20: (V1) บันทึกสำเร็จ, booking.review ถูกตั้งค่า | E20: บันทึกสำเร็จ | F20: Pass
A21: UT26-TC002 | B21: 10 / COMPLETED | C21: " นวดดีมาก " | D21: (V2) comment = "นวดดีมาก" | E21: comment = "นวดดีมาก" | F21: Pass
A22: UT26-TC003 | B22: 10 / COMPLETED | C22: " " | D22: (V3) comment = null | E22: comment = null | F22: Pass
A23: UT26-TC004 | B23: 10 / COMPLETED | C23: รีวิวหมอนวด T5 รวม 5, 4, 4 | D23: (V4) T5.averageRating = 4.33 | E23: T5.averageRating = 4.33 | F23: Pass
A24: UT26-TC005 | B24: 30 / COMPLETED (therapist = null) | C24: − | D24: (V5) บันทึกสำเร็จ ไม่เกิด NullPointerException | E24: บันทึกสำเร็จ | F24: Pass
A25: UT26-TC006 | B25: 999 | C25: − | D25: (I1) NotFoundException | E25: NotFoundException | F25: Pass
A26: UT26-TC007 | B26: 10 / CONFIRMED | C26: − | D26: (I2) ValidationException "...only be submitted for a completed booking" | E26: ValidationException | F26: Pass
A27: UT26-TC008 | B27: 10 / COMPLETED มีรีวิวแล้ว | C27: − | D27: (I3) ConflictException | E27: ConflictException | F27: Pass
A28: UT26-TC009 | B28: 10 / COMPLETED | C28: overallRating = null | D28: (I4) ValidationException | E28: ValidationException | F28: Pass

Sheet UT27_Login_DT
A1: Condition | B1: Rule#1 | C1: Rule#2 | D1: Rule#3 | E1: Rule#4
A2: C1: พบผู้ใช้จาก identifier | B2: N | C2: Y | D2: Y | E2: Y
A3: C2: isActive = true | B3: − | C3: N | D3: Y | E3: Y
A4: C3: รหัสผ่านถูกต้อง | B4: − | C4: − | D4: N | E4: Y
A5: Action
A6: A1: BusinessException 401 "อีเมลหรือรหัสผ่านไม่ถูกต้อง" | B6: X | D6: X
A7: A2: BusinessException 401 "บัญชีนี้ถูกระงับ..." | C7: X
A8: A3: ตั้ง lastLoginAt, save, คืน token + role | E8: X
A9: Impossible
A11: Test Case Design and Test Results
A13: Project Name: | B13: AuthServiceImpl.login | G13: Student ID: | H13: 673380049-4
A14: Test Strategy: | B14: Functional testing - Decision Table (Limited Entry) | G14: Designer: | H14: Piyachayanin
A15: Test Environtment: | B15: Lenovo LOQ 15AHP11, CPU AMD Ryzen 7 250, Memory 16 GB DDR5, GPU NVIDIA GeForce RTX 5050 Laptop, OS Window 11 | G15: Date: | H15: 09/10/2026
A16: Method under test: | B16: AuthResponseDTO login(LoginRequestDTO request) → ค้นหาด้วย email → username → เบอร์โทร
A17: Requirement อ้างอิง: | B17: UC-02 • SRS 7.4 (BCrypt, JWT)
A19: Rule# | B19: Test Case ID | C19: Input | F19: Expected Result | G19: Actual Result | H19: Status (Pass/Fail/No run)
C20: identifier | D20: password | E20: สภาพบัญชี
A21: R1 | B21: UT27-TC001 | C21: nobody@test.com | D21: x | E21: ไม่พบ | F21: BusinessException 401 "อีเมลหรือรหัสผ่านไม่ถูกต้อง" | G21: BusinessException 401 | H21: Pass
A22: R2 | B22: UT27-TC002 | C22: customer@test.com | D22: customer1234 | E22: isActive = false | F22: BusinessException 401 "บัญชีนี้ถูกระงับการใช้งาน..." • ไม่ตรวจรหัสผ่าน | G22: BusinessException 401 | H22: Pass
A23: R3 | B23: UT27-TC003 | C23: customer@test.com | D23: wrong | E23: active | F23: BusinessException 401 "อีเมลหรือรหัสผ่านไม่ถูกต้อง" • lastLoginAt ไม่เปลี่ยน | G23: BusinessException 401 | H23: Pass
A24: R4 | B24: UT27-TC004 | C24: customer@test.com | D24: customer1234 | E24: active | F24: สำเร็จ: token จาก JwtTokenProvider, role = CUSTOMER, lastLoginAt ถูกตั้ง, save 1 ครั้ง | G24: สำเร็จ | H24: Pass
A25: R4 | B25: UT27-TC005 | C25: customer | D25: customer1234 | E25: active (ค้นด้วย username) | F25: สำเร็จ (findByEmail ว่าง → findByUsername) | G25: สำเร็จ | H25: Pass
A26: R4 | B26: UT27-TC006 | C26: 081-000-3333 | D26: customer1234 | E26: active (ค้นด้วยเบอร์) | F26: สำเร็จ (ค้นถึง findByPhoneNumber) | G26: สำเร็จ | H26: Pass
A27: R4 | B27: UT27-TC007 | C27: " customer@test.com " | D27: customer1234 | E27: active | F27: สำเร็จ (identifier ถูก trim) | G27: สำเร็จ | H27: Pass

Sheet UT28_Register_EC
A1: Equivalence Class Design
A2: Valid EC | E2: Invalid EC
A3: EC ID | B3: Condition | E3: EC ID | F3: Condition
A4: V1 | B4: อีเมลและเบอร์ไม่ซ้ำ | E4: I1 | F4: อีเมลซ้ำ
A5: V2 | B5: ข้อมูลมีช่องว่างหน้า/หลัง → trim | E5: I2 | F5: เบอร์โทรซ้ำ
E6: I3 | F6: ซ้ำทั้งคู่ → แจ้งเรื่องอีเมลก่อน
A8: Test Case Design and Test Results
A10: Project Name: | B10: AuthServiceImpl.register | H10: Student ID: | I10: 673380049-4
A11: Test Strategy: | B11: Functional testing - Weak Robust Equivalence Class Testing | H11: Designer: | I11: Piyachayanin
A12: Test Environtment: | B12: Lenovo LOQ 15AHP11, CPU AMD Ryzen 7 250, Memory 16 GB DDR5, GPU NVIDIA GeForce RTX 5050 Laptop, OS Window 11 | H12: Date: | I12: 09/10/2026
A13: Method under test: | B13: AuthResponseDTO register(RegisterRequestDTO request)
A14: Requirement อ้างอิง: | B14: UC-01
A16: Test Case ID | B16: Input | E16: Expected Result | F16: Actual Result | G16: Status (Pass/Fail/No run)
B17: email | C17: phoneNumber | D17: สภาพข้อมูล
A18: UT28-TC001 | B18: new@test.com | C18: 0812223333 | D18: ไม่ซ้ำ | E18: (V1) save Customer: role CUSTOMER, username = email, passwordHash = "hashed" (ไม่เก็บรหัสจริง) • คืน token | F18: save Customer: role CUSTOMER, username = email, passwordHash = "hashed" | G18: Pass
A19: UT28-TC002 | B19: " new@test.com " | C19: " 0812223333 " | D19: ไม่ซ้ำ | E19: (V2) email และ phone ถูก trim | F19: email และ phone ถูก trim | G19: Pass
A20: UT28-TC003 | B20: customer@test.com | C20: 0812223333 | D20: อีเมลมีแล้ว | E20: (I1) ConflictException "อีเมลนี้ถูกใช้งานแล้ว..." • ไม่ save | F20: ConflictException | G20: Pass
A21: UT28-TC004 | B21: new@test.com | C21: 081-000-3333 | D21: เบอร์มีแล้ว | E21: (I2) ConflictException "เบอร์โทรศัพท์นี้ถูกใช้งานแล้ว..." | F21: ConflictException | G21: Pass
A22: UT28-TC005 | B22: customer@test.com | C22: 081-000-3333 | D22: ซ้ำทั้งคู่ | E22: (I3) ConflictException เรื่องอีเมล | F22: ConflictException | G22: Pass

Sheet UT29_UpdateProfile_DT
A1: Condition | B1: Rule#1 | C1: Rule#2 | D1: Rule#3 | E1: Rule#4 | F1: Rule#5 | G1: Rule#6 | H1: Rule#7
A2: C1: พบผู้ใช้ | B2: N | C2: Y | D2: Y | E2: Y | F2: Y | G2: Y | H2: Y
A3: C2: อีเมลซ้ำกับคนอื่น | B3: − | C3: Y | D3: N | E3: N | F3: N | G3: N | H3: N
A4: C3: เบอร์ซ้ำกับคนอื่น | B4: − | C4: − | D4: Y | E4: N | F4: N | G4: N | H4: N
A5: C4: ส่ง newPassword | B5: − | C5: − | D5: − | E5: Y | F5: Y | G5: N | H5: N
A6: C5: currentPassword ถูกต้อง | B6: − | C6: − | D6: − | E6: N | F6: Y | G6: − | H6: −
A7: C6: ผู้ใช้เป็น Customer | B7: − | C7: − | D7: − | E7: − | F7: − | G7: Y | H7: N
A8: Action
A9: A1: NotFoundException | B9: X
A10: A2: ConflictException | C10: X | D10: X
A11: A3: ValidationException รหัสผ่านปัจจุบันไม่ถูกต้อง | E11: X
A12: A4: เปลี่ยน passwordHash | F12: X
A13: A5: บันทึกชื่อ/อีเมล/เบอร์ (trim) | F13: X | G13: X | H13: X
A14: A6: บันทึก healthNotes, preferredPressure | G14: X
A15: Impossible
A17: Test Case Design and Test Results
A19: Project Name: | B19: UserServiceImpl.updateProfile | G19: Student ID: | H19: 673380049-4
A20: Test Strategy: | B20: Functional testing - Decision Table (Limited Entry) | G20: Designer: | H20: Piyachayanin
A21: Test Environtment: | B21: Lenovo LOQ 15AHP11, CPU AMD Ryzen 7 250, Memory 16 GB DDR5, GPU NVIDIA GeForce RTX 5050 Laptop, OS Window 11 | G21: Date: | H21: 09/10/2026
A22: Method under test: | B22: UserResponseDTO updateProfile(Long userId, UpdateProfileRequestDTO request)
A23: Requirement อ้างอิง: | B23: SRS 3.4 (หน้าโปรไฟล์) • BR-SEC-01
A25: Rule# | B25: Test Case ID | C25: Input | F25: Expected Result | G25: Actual Result | H25: Status (Pass/Fail/No run)
C26: userId | D26: request | E26: สภาพข้อมูล
A27: R1 | B27: UT29-TC001 | C27: 999 | D27: ข้อมูลปกติ | E27: − | F27: NotFoundException | G27: NotFoundException | H27: Pass
A28: R2 | B28: UT29-TC002 | C28: 1 | D28: email = owner@fiwdee... | E28: อีเมลเป็นของ user#60 | F28: ConflictException อีเมลซ้ำ • ไม่ save | G28: ConflictException | H28: Pass
A29: R3 | B29: UT29-TC003 | C29: 1 | D29: phone ซ้ำ | E29: เบอร์เป็นของ user#50 | F29: ConflictException เบอร์ซ้ำ | G29: ConflictException | H29: Pass
A30: R4 | B30: UT29-TC004 | C30: 1 | D30: new = "newpass123", current = "wrong" | E30: − | F30: ValidationException "รหัสผ่านปัจจุบันไม่ถูกต้อง" | G30: ValidationException | H30: Pass
A31: R4 | B31: UT29-TC005 | C31: 1 | D31: new = "newpass123", current = "" | E31: − | F31: ValidationException | G31: ValidationException | H31: Pass
A32: R5 | B32: UT29-TC006 | C32: 1 | D32: new = "newpass123", current = "customer1234" | E32: − | F32: passwordHash = encode("newpass123") • save | G32: passwordHash = encode("newpass123") • save | H32: Pass
A33: R6 | B33: UT29-TC007 | C33: 1 (Customer) | D33: ไม่ส่ง newPassword, healthNotes = "ความดันสูง" | E33: − | F33: passwordHash ไม่เปลี่ยน, healthNotes ถูกบันทึก | G33: passwordHash ไม่เปลี่ยน, healthNotes ถูกบันทึก | H33: Pass
A34: R7 | B34: UT29-TC008 | C34: 50 (Receptionist) | D34: fullName = " สมใจ " | E34: − | F34: fullName = "สมใจ" • ไม่มี field ของลูกค้า | G34: fullName = "สมใจ" • ไม่มี field ของลูกค้า | H34: Pass

Sheet UT30_UserSession_BVA
A1: Test Case Design and Test Results | J1: เวลาหลัง touch ล่าสุด
I2: min | J2: 0:00
A3: Project Name: | B3: UserSessionServiceImpl – สถานะออนไลน์ (หน้าต่าง 15 นาที) | E3: Student ID: | F3: 673380049-4 | I3: nom | J3: 5:00
A4: Test Strategy: | B4: Functional testing - Robustness Testing (ขอบด้านเดียว) | E4: Designer: | F4: Piyachayanin | I4: ขอบ-1 | J4: 14:59
A5: Test Environtment: | B5: Lenovo LOQ 15AHP11, CPU AMD Ryzen 7 250, Memory 16 GB DDR5, GPU NVIDIA GeForce RTX 5050 Laptop, OS Window 11 | E5: Date: | F5: 09/10/2026 | I5: ขอบ | J5: 15:00
A6: Method under test: | B6: touch(userId), isOnline(userId), getSessionStart(userId) → expired เมื่อ Duration.toMinutes() ≥ 15 | I6: ขอบ+1 | J6: 15:01
A7: Requirement อ้างอิง: | B7: TASKS 2.14 (online window 15 นาที)
A9: Test Case ID | B9: Input | D9: Expected Result | E9: Actual Result | F9: Status (Pass/Fail/No run)
B10: เวลาหลัง touch ล่าสุด (นาที:วินาที) | C10: เหตุการณ์
A11: UT30-TC001 | B11: 0:00 | C11: touch แล้วเช็กทันที | D11: isOnline = true, getSessionStart = เวลา touch แรก | E11: isOnline = true, getSessionStart = เวลา touch แรก | F11: Pass
A12: UT30-TC002 | B12: 5:00 | C12: − | D12: isOnline = true | E12: isOnline = true | F12: Pass
A13: UT30-TC003 | B13: 14:59 | C13: − | D13: isOnline = true | E13: isOnline = true | F13: Pass
A14: UT30-TC004 | B14: 15:00 | C14: − | D14: isOnline = false, getSessionStart = null | E14: isOnline = false, getSessionStart = null | F14: Pass
A15: UT30-TC005 | B15: 15:01 | C15: − | D15: isOnline = false | E15: isOnline = false | F15: Pass
A16: UT30-TC006 | B16: − | C16: ไม่เคย touch | D16: isOnline = false | E16: isOnline = false | F16: Pass
A17: UT30-TC007 | B17: 2:00 | C17: endSession แล้วเช็ก | D17: isOnline = false | E17: isOnline = false | F17: Pass
A18: UT30-TC008 | B18: 20:00 | C18: touch ใหม่หลังหมดอายุ | D18: isOnline = true และ getSessionStart = เวลา touch ใหม่ (เริ่ม session ใหม่) | E18: isOnline = true และ getSessionStart = เวลา touch ใหม่ (เริ่ม session ใหม่) | F18: Pass

Sheet UT31_JwtToken_EC
A1: Equivalence Class Design
A2: Valid EC | E2: Invalid EC
A3: EC ID | B3: Condition | E3: EC ID | F3: Condition
A4: V1 | B4: token ที่ระบบออกให้และยังไม่หมดอายุ | E4: I1 | F4: หมดอายุ (expiration-ms = -1000)
E5: I2 | F5: payload ถูกแก้
E6: I3 | F6: เซ็นด้วย key อื่น
E7: I4 | F7: รูปแบบผิด เช่น "abc"
E8: I5 | F8: null หรือ ""
A10: Test Case Design and Test Results
A12: Project Name: | B12: JwtTokenProvider | H12: Student ID: | I12: 673380049-4
A13: Test Strategy: | B13: Functional testing - Weak Robust Equivalence Class Testing | H13: Designer: | I13: Piyachayanin
A14: Test Environtment: | B14: Lenovo LOQ 15AHP11, CPU AMD Ryzen 7 250, Memory 16 GB DDR5, GPU NVIDIA GeForce RTX 5050 Laptop, OS Window 11 | H14: Date: | I14: 09/10/2026
A15: Method under test: | B15: generateToken(User) • validateToken(String) • getUsernameFromToken(String)
A16: Requirement อ้างอิง: | B16: SRS 7.4 (JWT Bearer Token)
A18: Test Case ID | B18: Input | D18: Expected Result | E18: Actual Result | F18: Status (Pass/Fail/No run)
B19: token | C19: เมธอด
A20: UT31-TC001 | B20: generateToken(customer) | C20: validateToken | D20: (V1) true | E20: TRUE | F20: Pass
A21: UT31-TC002 | B21: generateToken(customer) | C21: getUsernameFromToken | D21: (V1) ค่าเท่ากับ user.getUsername() | E21: ค่าเท่ากับ user.getUsername() | F21: Pass
A22: UT31-TC003 | B22: token ที่ expiration-ms = -1000 | C22: validateToken | D22: (I1) false ไม่โยน Exception | E22: false ไม่โยน Exception | F22: Pass
A23: UT31-TC004 | B23: แก้ตัวอักษรใน payload | C23: validateToken | D23: (I2) false | E23: FALSE | F23: Pass
A24: UT31-TC005 | B24: token จาก provider ที่ใช้ secret อื่น | C24: validateToken | D24: (I3) false | E24: FALSE | F24: Pass
A25: UT31-TC006 | B25: "abc" | C25: validateToken | D25: (I4) false | E25: FALSE | F25: Pass
A26: UT31-TC007 | B26: null และ "" | C26: validateToken | D26: (I5) false | E26: FALSE | F26: Pass

Sheet UT32_RoomService_EC
A1: Equivalence Class Design
A2: Valid EC | E2: Invalid EC
A3: EC ID | B3: Condition | E3: EC ID | F3: Condition
A4: V1 | B4: เลขห้องใหม่ไม่ซ้ำ | E4: I1 | F4: เลขห้องซ้ำ (ต่างตัวพิมพ์)
A5: V2 | B5: แก้ไขห้องโดยใช้เลขเดิมของตัวเอง | E5: I2 | F5: แก้เป็นเลขของห้องอื่น
A6: V3 | B6: ลบ = ปิดใช้งาน | E6: I3 | F6: id ไม่มีอยู่
A7: V4 | B7: getRooms(activeOnly = true)
A9: Test Case Design and Test Results
A11: Project Name: | B11: RoomServiceImpl | H11: Student ID: | I11: 673380049-4
A12: Test Strategy: | B12: Functional testing - Weak Robust Equivalence Class Testing | H12: Designer: | I12: Piyachayanin
A13: Test Environtment: | B13: Lenovo LOQ 15AHP11, CPU AMD Ryzen 7 250, Memory 16 GB DDR5, GPU NVIDIA GeForce RTX 5050 Laptop, OS Window 11 | H13: Date: | I13: 09/10/2026
A14: Method under test: | B14: createRoom, updateRoom, deleteRoom, getRooms
A15: Requirement อ้างอิง: | B15: UC-24 • BR-RES-01
A17: Test Case ID | B17: Input | D17: Expected Result | E17: Actual Result | F17: Status (Pass/Fail/No run)
B18: เมธอด | C18: input
A19: UT32-TC001 | B19: createRoom | C19: " R104 ", SINGLE, 1, 15 | D19: (V1) save: roomNumber "R104", AVAILABLE, isActive true | E19: save: roomNumber "R104", AVAILABLE, isActive true | F19: Pass
A20: UT32-TC002 | B20: updateRoom(101) | C20: "R101", VIP, 2, 20 | D20: (V2) สำเร็จ roomType VIP | E20: สำเร็จ roomType VIP | F20: Pass
A21: UT32-TC003 | B21: deleteRoom(102) | C21: − | D21: (V3) isActive = false และ save (ไม่ลบจริง) | E21: isActive = false และ save | F21: Pass
A22: UT32-TC004 | B22: getRooms(true) | C22: − | D22: (V4) เรียก findByIsActiveTrue ไม่เรียก findAll | E22: เรียก findByIsActiveTrue ไม่เรียก findAl | F22: Pass
A23: UT32-TC005 | B23: createRoom | C23: "r101" | D23: (I1) ConflictException "Room number already exists" | E23: ConflictException | F23: Pass
A24: UT32-TC006 | B24: updateRoom(101) | C24: "R102" | D24: (I2) ConflictException | E24: ConflictException | F24: Pass
A25: UT32-TC007 | B25: updateRoom(999) / deleteRoom(999) | C25: − | D25: (I3) NotFoundException | E25: NotFoundException | F25: Pass

Sheet UT33_ServiceCatalog_EC
A1: Equivalence Class Design
A2: Valid EC | E2: Invalid EC
A3: EC ID | B3: Condition | E3: EC ID | F3: Condition
A4: V1 | B4: รหัสใหม่ + option อย่างน้อย 1 รายการ | E4: I1 | F4: durationOptions ว่างหรือ null
A5: V2 | B5: duration = 1 (ค่าบวกต่ำสุด) | E5: I2 | F5: duration ≤ 0
A6: V3 | B6: price = 0.00 | E6: I3 | F6: price < 0
A7: V4 | B7: update ด้วยรหัสเดิมของตัวเอง | E7: I4 | F7: รหัสซ้ำ (ต่างตัวพิมพ์)
E8: I5 | F8: getActiveService ของบริการที่ปิดอยู่
A10: Test Case Design and Test Results
A12: Project Name: | B12: ServiceCatalogServiceImpl | H12: Student ID: | I12: 673380049-4
A13: Test Strategy: | B13: Functional testing - Weak Robust Equivalence Class Testing (ใช้ค่าขอบเป็นตัวแทนคลาส) | H13: Designer: | I13: Piyachayanin
A14: Test Environtment: | B14: Lenovo LOQ 15AHP11, CPU AMD Ryzen 7 250, Memory 16 GB DDR5, GPU NVIDIA GeForce RTX 5050 Laptop, OS Window 11 | H14: Date: | I14: 09/10/2026
A15: Method under test: | B15: createService, updateService, getActiveService, deleteService
A16: Requirement อ้างอิง: | B16: UC-25 • SRS 6.3
A18: Test Case ID | B18: Input | E18: Expected Result | F18: Actual Result | G18: Status (Pass/Fail/No run)
B19: เมธอด | C19: serviceCode | D19: durationOptions
A20: UT33-TC001 | B20: createService | C20: AROMA-01 | D20: [60/800] | E20: (V1) save, isActive true, option 1 รายการ active | F20: save, isActive true, option 1 รายการ active | G20: Pass
A21: UT33-TC002 | B21: createService | C21: AROMA-02 | D21: [1/800] | E21: (V2) สำเร็จ | F21: สำเร็จ | G21: Pass
A22: UT33-TC003 | B22: createService | C22: AROMA-03 | D22: [60/0.00] | E22: (V3) สำเร็จ | F22: สำเร็จ | G22: Pass
A23: UT33-TC004 | B23: updateService(1) | C23: thai-01 | D23: [60/600, 90/850] | E23: (V4) สำเร็จ option ถูกแทนที่เป็น 2 รายการ | F23: สำเร็จ | G23: Pass
A24: UT33-TC005 | B24: createService | C24: AROMA-04 | D24: [] และ null | E24: (I1) ValidationException "At least one duration option is required" | F24: ValidationException | G24: Pass
A25: UT33-TC006 | B25: createService | C25: AROMA-05 | D25: [0/800] และ [-1/800] | E25: (I2) ValidationException | F25: ValidationException | G25: Pass
A26: UT33-TC007 | B26: createService | C26: AROMA-06 | D26: [60/-0.01] | E26: (I3) ValidationException | F26: ValidationException | G26: Pass
A27: UT33-TC008 | B27: createService | C27: thai-01 | D27: [60/600] | E27: (I4) ConflictException "Service code already exists" | F27: ConflictException | G27: Pass
A28: UT33-TC009 | B28: getActiveService(3) | C28: บริการ 3 inactive | D28: − | E28: (I5) NotFoundException | F28: NotFoundException | G28: Pass

Sheet UT34_Schedule_Shift_BVA
A1: Test Case Design and Test Results | J1: ความยาวกะ (นาที) | K1: ช่องว่างระหว่างกะ (นาที)
I2: ขอบ-1 | J2: 0 | K2: -1
A3: Project Name: | B3: TherapistServiceImpl.updateSchedule – กะทำงาน | E3: Student ID: | F3: 673380049-4 | I3: ขอบ | J3: 1 | K3: 0
A4: Test Strategy: | B4: Functional testing - Robustness Testing (ขอบด้านเดียว) | E4: Designer: | F4: Piyachayanin | I4: ขอบ+1 | J4: 2 | K4: 1
A5: Test Environtment: | B5: Lenovo LOQ 15AHP11, CPU AMD Ryzen 7 250, Memory 16 GB DDR5, GPU NVIDIA GeForce RTX 5050 Laptop, OS Window 11 | E5: Date: | F5: 09/10/2026 | I5: nom | J5: 480 | K5: 60
A6: Method under test: | B6: updateSchedule(therapistId, request) → validateShifts: end > start และกะต้องไม่ทับกัน
A7: Requirement อ้างอิง: | B7: UC-27 • SRS 6.4 (Work Shifts)
A9: Test Case ID | B9: Input | D9: Expected Result | E9: Actual Result | F9: Status (Pass/Fail/No run)
B10: dayOff | C10: shifts
A11: UT34-TC001 | B11: false | C11: [10:00–18:00] | D11: บันทึก 1 กะ ชื่อ "Shift", status ACTIVE (nom) | E11: บันทึก 1 กะ ชื่อ "Shift", status ACTIVE | F11: Pass
A12: UT34-TC002 | B12: false | C12: [10:00–10:00] | D12: ValidationException "Shift end time must be after start time" | E12: ValidationException | F12: Pass
A13: UT34-TC003 | B13: false | C13: [10:00–10:01] | D13: บันทึกสำเร็จ | E13: บันทึกสำเร็จ | F13: Pass
A14: UT34-TC004 | B14: false | C14: [10:00–10:02] | D14: บันทึกสำเร็จ | E14: บันทึกสำเร็จ | F14: Pass
A15: UT34-TC005 | B15: false | C15: [10:00–14:00, 13:59–18:00] | D15: ValidationException "Work shifts must not overlap" | E15: ValidationException | F15: Pass
A16: UT34-TC006 | B16: false | C16: [10:00–14:00, 14:00–18:00] | D16: บันทึก 2 กะ | E16: บันทึก 2 กะ | F16: Pass
A17: UT34-TC007 | B17: false | C17: [10:00–14:00, 14:01–18:00] | D17: บันทึก 2 กะ | E17: บันทึก 2 กะ | F17: Pass
A18: UT34-TC008 | B18: false | C18: [15:00–18:00, 10:00–14:00] (ไม่เรียงเวลา) | D18: บันทึกสำเร็จ (โค้ดเรียงก่อนตรวจ) | E18: บันทึกสำเร็จ | F18: Pass
A19: UT34-TC009 | B19: true | C19: [10:00–18:00] | D19: ValidationException "Day-off schedules cannot contain work shifts" | E19: ValidationException | F19: Pass
A20: UT34-TC010 | B20: true | C20: [] | D20: บันทึกวันหยุด ไม่มีกะ | E20: บันทึกวันหยุด ไม่มีกะ | F20: Pass

Sheet UT35_ShopHours_BVA
A1: Test Case Design and Test Results | J1: closeTime − openTime (นาที)
I2: ขอบ-1 | J2: -1
A3: Project Name: | B3: ShopServiceImpl.updateShop – เวลาเปิด–ปิด | E3: Student ID: | F3: 673380049-4 | I3: ขอบ | J3: 0
A4: Test Strategy: | B4: Functional testing - Robustness Testing (ขอบด้านเดียว) | E4: Designer: | F4: Piyachayanin | I4: ขอบ+1 | J4: 1
A5: Test Environtment: | B5: Lenovo LOQ 15AHP11, CPU AMD Ryzen 7 250, Memory 16 GB DDR5, GPU NVIDIA GeForce RTX 5050 Laptop, OS Window 11 | E5: Date: | F5: 09/10/2026 | I5: nom | J5: 720
A6: Method under test: | B6: updateShop(request) : ถ้าไม่ปิด closeTime ต้องหลัง openTime, วันห้ามซ้ำ, ต้องมีอย่างน้อย 1 วัน
A7: Requirement อ้างอิง: | B7: UC-23 / SRS 6 (เวลาทำการ) • BR-BKG-02
A9: Test Case ID | B9: Input | D9: Expected Result | E9: Actual Result | F9: Status (Pass/Fail/No run)
B10: businessHours | C10: closed
A11: UT35-TC001 | B11: MONDAY 10:00–22:00 | C11: false | D11: บันทึกสำเร็จ (nom) | E11: บันทึกสำเร็จ | F11: Pass
A12: UT35-TC002 | B12: MONDAY 10:00–09:59 | C12: false | D12: ValidationException "Closing time must be after opening time" | E12: ValidationException | F12: Pass
A13: UT35-TC003 | B13: MONDAY 10:00–10:00 | C13: false | D13: ValidationException | E13: ValidationException | F13: Pass
A14: UT35-TC004 | B14: MONDAY 10:00–10:01 | C14: false | D14: บันทึกสำเร็จ | E14: บันทึกสำเร็จ | F14: Pass
A15: UT35-TC005 | B15: SUNDAY 10:00–09:00 | C15: true | D15: บันทึกสำเร็จ (วันปิดไม่ตรวจเวลา) | E15: บันทึกสำเร็จ | F15: Pass
A16: UT35-TC006 | B16: MONDAY 2 แถว | C16: false | D16: ValidationException "Duplicate business hours day: MONDAY" | E16: ValidationException | F16: Pass
A17: UT35-TC007 | B17: [] (ว่าง) | C17: − | D17: ValidationException "Business hours for the week are required" | E17: ValidationException | F17: Pass
A18: UT35-TC008 | B18: ไม่มีร้าน active | C18: − | D18: NotFoundException | E18: NotFoundException | F18: Pass

Sheet UT36_RevenueReport_BVA
A1: Test Case Design and Test Results | K1: end − start (วัน) | L1: refundedAt เทียบขอบล่าง | M1: refundedAt เทียบขอบบน
J2: ขอบ-1 | K2: -1 | L2: 31/10 23:59:59.999999999 | M2: 30/11 23:59:59.999999998
A3: Project Name: | B3: ReportServiceImpl.getRevenueReport – ช่วงวันที่ | F3: Student ID: | G3: 673380049-4 | J3: ขอบ | K3: 0 | L3: 01/11 00:00 | M3: 30/11 23:59:59.999999999
A4: Test Strategy: | B4: Functional testing - Robustness Testing (ขอบด้านเดียว) | F4: Designer: | G4: Piyachayanin | J4: ขอบ+1 | K4: 1 | L4: 01/11 00:00:00.000000001 | M4: 01/12 00:00
A5: Test Environtment: | B5: Lenovo LOQ 15AHP11, CPU AMD Ryzen 7 250, Memory 16 GB DDR5, GPU NVIDIA GeForce RTX 5050 Laptop, OS Window 11 | F5: Date: | G5: 09/10/2026
A6: Method under test: | B6: RevenueReportDTO getRevenueReport(LocalDate startDate, LocalDate endDate)
A7: Requirement อ้างอิง: | B7: UC-22 • TASKS 3.1
A9: Test Case ID | B9: Input | E9: Expected Result | F9: Actual Result | G9: Status (Pass/Fail/No run)
B10: startDate | C10: endDate | D10: refundedAt
A11: UT36-TC001 | B11: 2026-11-02 | C11: 2026-11-01 | D11: − | E11: ValidationException "Start date must be before or equal to end date" | F11: ValidationException | G11: Pass
A12: UT36-TC002 | B12: 2026-11-01 | C12: 2026-11-01 | D12: − | E12: สำเร็จ (ช่วง 1 วัน) | F12: สำเร็จ | G12: Pass
A13: UT36-TC003 | B13: 2026-11-01 | C13: 2026-11-02 | D13: − | E13: สำเร็จ | F13: สำเร็จ | G13: Pass
A14: UT36-TC004 | B14: 2026-11-01 | C14: 2026-11-30 | D14: 31/10 23:59:59.999999999 | E14: refundedTotal = 0 (นอกช่วง) | F14: refundedTotal = 0 | G14: Pass
A15: UT36-TC005 | B15: 2026-11-01 | C15: 2026-11-30 | D15: 01/11 00:00 | E15: refundedTotal = 100.00 | F15: refundedTotal = 100.00 | G15: Pass
A16: UT36-TC006 | B16: 2026-11-01 | C16: 2026-11-30 | D16: 01/11 00:00:00.000000001 | E16: refundedTotal = 100.00 | F16: refundedTotal = 100.00 | G16: Pass
A17: UT36-TC007 | B17: 2026-11-01 | C17: 2026-11-30 | D17: 30/11 23:59:59.999999998 | E17: refundedTotal = 100.00 | F17: refundedTotal = 100.00 | G17: Pass
A18: UT36-TC008 | B18: 2026-11-01 | C18: 2026-11-30 | D18: 30/11 23:59:59.999999999 | E18: refundedTotal = 100.00 | F18: refundedTotal = 100.00 | G18: Pass
A19: UT36-TC009 | B19: 2026-11-01 | C19: 2026-11-30 | D19: 01/12 00:00 | E19: refundedTotal = 0 | F19: refundedTotal = 0 | G19: Pass
A20: UT36-TC010 | B20: null | C20: 2026-11-30 | D20: − | E20: ValidationException "Start date and end date must not be null" | F20: ValidationException | G20: Pass
